{
"meta":{"test_sets":[],"test_metrics":[],"learn_metrics":[{"best_value":"Min","name":"MultiClass"}],"launch_mode":"Train","parameters":"","iteration_count":1000,"learn_sets":["learn"],"name":"experiment"},
"iterations":[
{"learn":[1.386393484],"iteration":0,"passed_time":0.06760297084,"remaining_time":67.53536787},
{"learn":[1.236124242],"iteration":1,"passed_time":0.08404687018,"remaining_time":41.93938822},
{"learn":[1.121727274],"iteration":2,"passed_time":0.1006868954,"remaining_time":33.46161158},
{"learn":[1.032650476],"iteration":3,"passed_time":0.1169192533,"remaining_time":29.11289408},
{"learn":[0.9583164443],"iteration":4,"passed_time":0.1317397192,"remaining_time":26.21620413},
{"learn":[0.8983060748],"iteration":5,"passed_time":0.1486090244,"remaining_time":24.6195617},
{"learn":[0.8475707707],"iteration":6,"passed_time":0.1650590677,"remaining_time":23.41480774},
{"learn":[0.8042720619],"iteration":7,"passed_time":0.1805260153,"remaining_time":22.3852259},
{"learn":[0.7671814791],"iteration":8,"passed_time":0.1973179494,"remaining_time":21.72689865},
{"learn":[0.7349357766],"iteration":9,"passed_time":0.2122821255,"remaining_time":21.01593042},
{"learn":[0.7068180084],"iteration":10,"passed_time":0.2287780361,"remaining_time":20.56922524},
{"learn":[0.6824095242],"iteration":11,"passed_time":0.2446273,"remaining_time":20.14098103},
{"learn":[0.6609107822],"iteration":12,"passed_time":0.2622257026,"remaining_time":19.90898219},
{"learn":[0.6419374117],"iteration":13,"passed_time":0.2789431241,"remaining_time":19.64556574},
{"learn":[0.625700724],"iteration":14,"passed_time":0.2957370116,"remaining_time":19.42006376},
{"learn":[0.6114853611],"iteration":15,"passed_time":0.3122745135,"remaining_time":19.20488258},
{"learn":[0.5983834786],"iteration":16,"passed_time":0.3271954607,"remaining_time":18.91959635},
{"learn":[0.5858143464],"iteration":17,"passed_time":0.3433757475,"remaining_time":18.73305467},
{"learn":[0.5755995576],"iteration":18,"passed_time":0.3580738093,"remaining_time":18.48791615},
{"learn":[0.5659276338],"iteration":19,"passed_time":0.3731691254,"remaining_time":18.28528715},
{"learn":[0.5578282285],"iteration":20,"passed_time":0.3901641158,"remaining_time":18.1890795},
{"learn":[0.5503095775],"iteration":21,"passed_time":0.4051886251,"remaining_time":18.01247615},
{"learn":[0.543562748],"iteration":22,"passed_time":0.4212468567,"remaining_time":17.89383387},
{"learn":[0.5368781816],"iteration":23,"passed_time":0.4370178094,"remaining_time":17.77205758},
{"learn":[0.5309040021],"iteration":24,"passed_time":0.450972688,"remaining_time":17.58793483},
{"learn":[0.5257102796],"iteration":25,"passed_time":0.4670991285,"remaining_time":17.49825197},
{"learn":[0.5212251693],"iteration":26,"passed_time":0.4841237026,"remaining_time":17.4463838},
{"learn":[0.5170274584],"iteration":27,"passed_time":0.5020045577,"remaining_time":17.42672965},
{"learn":[0.5129968294],"iteration":28,"passed_time":0.518386683,"remaining_time":17.35701618},
{"learn":[0.5093556705],"iteration":29,"passed_time":0.5358860083,"remaining_time":17.32698094},
{"learn":[0.505621573],"iteration":30,"passed_time":0.5511915673,"remaining_time":17.22918157},
{"learn":[0.5025746407],"iteration":31,"passed_time":0.5676644197,"remaining_time":17.1718487},
{"learn":[0.4999747104],"iteration":32,"passed_time":0.5838526825,"remaining_time":17.10865285},
{"learn":[0.4969744902],"iteration":33,"passed_time":0.599451058,"remaining_time":17.03146241},
{"learn":[0.4945171988],"iteration":34,"passed_time":0.6151623477,"remaining_time":16.96090473},
{"learn":[0.4921688784],"iteration":35,"passed_time":0.6320844015,"remaining_time":16.92581564},
{"learn":[0.4901492874],"iteration":36,"passed_time":0.6478347617,"remaining_time":16.86121285},
{"learn":[0.488597948],"iteration":37,"passed_time":0.6633774485,"remaining_time":16.79392383},
{"learn":[0.4868720889],"iteration":38,"passed_time":0.6804490591,"remaining_time":16.76696271},
{"learn":[0.4852829443],"iteration":39,"passed_time":0.6963926773,"remaining_time":16.71342425},
{"learn":[0.4838825607],"iteration":40,"passed_time":0.7106189808,"remaining_time":16.62155128},
{"learn":[0.4823635142],"iteration":41,"passed_time":0.7259596755,"remaining_time":16.5587945},
{"learn":[0.4807814196],"iteration":42,"passed_time":0.7412069646,"remaining_time":16.49616431},
{"learn":[0.4797084901],"iteration":43,"passed_time":0.756226625,"remaining_time":16.43074212},
{"learn":[0.4782280619],"iteration":44,"passed_time":0.7721843227,"remaining_time":16.38746729},
{"learn":[0.4768267796],"iteration":45,"passed_time":0.7890079767,"remaining_time":16.36333934},
{"learn":[0.4754511508],"iteration":46,"passed_time":0.8033122867,"remaining_time":16.28843849},
{"learn":[0.4744150913],"iteration":47,"passed_time":0.8189765547,"remaining_time":16.243035},
{"learn":[0.4732323694],"iteration":48,"passed_time":0.8343924312,"remaining_time":16.19402453},
{"learn":[0.4720330778],"iteration":49,"passed_time":0.8496384921,"remaining_time":16.14313135},
{"learn":[0.4710812818],"iteration":50,"passed_time":0.8652234317,"remaining_time":16.09994189},
{"learn":[0.4703441085],"iteration":51,"passed_time":0.880221075,"remaining_time":16.04710729},
{"learn":[0.4692076815],"iteration":52,"passed_time":0.8959270645,"remaining_time":16.00835717},
{"learn":[0.4683830417],"iteration":53,"passed_time":0.9122903984,"remaining_time":15.98197624},
{"learn":[0.46735039],"iteration":54,"passed_time":0.9267381677,"remaining_time":15.9230467},
{"learn":[0.4665292736],"iteration":55,"passed_time":0.9417099278,"remaining_time":15.87453878},
{"learn":[0.4656984822],"iteration":56,"passed_time":0.9594097471,"remaining_time":15.8723402},
{"learn":[0.4649877786],"iteration":57,"passed_time":0.9743469774,"remaining_time":15.82473884},
{"learn":[0.4641469809],"iteration":58,"passed_time":0.9903378864,"remaining_time":15.79505002},
{"learn":[0.4635692753],"iteration":59,"passed_time":1.005478432,"remaining_time":15.75249543},
{"learn":[0.4629372199],"iteration":60,"passed_time":1.022129207,"remaining_time":15.73408731},
{"learn":[0.4625508775],"iteration":61,"passed_time":1.037243715,"remaining_time":15.69249362},
{"learn":[0.4618953048],"iteration":62,"passed_time":1.052990782,"remaining_time":15.66114862},
{"learn":[0.461289086],"iteration":63,"passed_time":1.067399084,"remaining_time":15.61071161},
{"learn":[0.4607127953],"iteration":64,"passed_time":1.082326476,"remaining_time":15.56885008},
{"learn":[0.4601247987],"iteration":65,"passed_time":1.097046901,"remaining_time":15.52487585},
{"learn":[0.4597144674],"iteration":66,"passed_time":1.1131025,"remaining_time":15.50036765},
{"learn":[0.4589452576],"iteration":67,"passed_time":1.129240828,"remaining_time":15.47724193},
{"learn":[0.4585598105],"iteration":68,"passed_time":1.144214424,"remaining_time":15.43860331},
{"learn":[0.4579913631],"iteration":69,"passed_time":1.158966622,"remaining_time":15.3976994},
{"learn":[0.4574335583],"iteration":70,"passed_time":1.173924963,"remaining_time":15.36022944},
{"learn":[0.4568514136],"iteration":71,"passed_time":1.1891882,"remaining_time":15.32731457},
{"learn":[0.4563928927],"iteration":72,"passed_time":1.204552788,"remaining_time":15.29617034},
{"learn":[0.4556360221],"iteration":73,"passed_time":1.22196729,"remaining_time":15.29110419},
{"learn":[0.4552108113],"iteration":74,"passed_time":1.236815502,"remaining_time":15.25405785},
{"learn":[0.4548725792],"iteration":75,"passed_time":1.251716683,"remaining_time":15.21823968},
{"learn":[0.454331218],"iteration":76,"passed_time":1.268026848,"remaining_time":15.1998543},
{"learn":[0.4539849113],"iteration":77,"passed_time":1.283476963,"remaining_time":15.17135589},
{"learn":[0.4533951214],"iteration":78,"passed_time":1.299187503,"remaining_time":15.14622392},
{"learn":[0.4531555317],"iteration":79,"passed_time":1.313867133,"remaining_time":15.10947202},
{"learn":[0.452606025],"iteration":80,"passed_time":1.328431174,"remaining_time":15.07195369},
{"learn":[0.4522770406],"iteration":81,"passed_time":1.343108251,"remaining_time":15.03626066},
{"learn":[0.4518773969],"iteration":82,"passed_time":1.358917663,"remaining_time":15.0135843},
{"learn":[0.4514551713],"iteration":83,"passed_time":1.372844643,"remaining_time":14.97054396},
{"learn":[0.4508650659],"iteration":84,"passed_time":1.387422571,"remaining_time":14.93519592},
{"learn":[0.4502883649],"iteration":85,"passed_time":1.402224281,"remaining_time":14.90270922},
{"learn":[0.4500170762],"iteration":86,"passed_time":1.416968617,"remaining_time":14.87002698},
{"learn":[0.449599031],"iteration":87,"passed_time":1.431430771,"remaining_time":14.83482799},
{"learn":[0.4493230353],"iteration":88,"passed_time":1.446351735,"remaining_time":14.80479135},
{"learn":[0.4489517409],"iteration":89,"passed_time":1.462453594,"remaining_time":14.78703078},
{"learn":[0.4485916988],"iteration":90,"passed_time":1.4778269,"remaining_time":14.76202915},
{"learn":[0.4479775462],"iteration":91,"passed_time":1.494183097,"remaining_time":14.74693753},
{"learn":[0.447655062],"iteration":92,"passed_time":1.508845712,"remaining_time":14.71530173},
{"learn":[0.4473390638],"iteration":93,"passed_time":1.524010449,"remaining_time":14.68886667},
{"learn":[0.4471378409],"iteration":94,"passed_time":1.538840883,"remaining_time":14.6594842},
{"learn":[0.446591905],"iteration":95,"passed_time":1.555475783,"remaining_time":14.64739695},
{"learn":[0.4462642141],"iteration":96,"passed_time":1.570008188,"remaining_time":14.61564323},
{"learn":[0.4459051747],"iteration":97,"passed_time":1.585628295,"remaining_time":14.59425227},
{"learn":[0.4454830335],"iteration":98,"passed_time":1.601188586,"remaining_time":14.5724335},
{"learn":[0.4451245048],"iteration":99,"passed_time":1.616449514,"remaining_time":14.54804563},
{"learn":[0.4446890465],"iteration":100,"passed_time":1.631732398,"remaining_time":14.52403392},
{"learn":[0.4443939663],"iteration":101,"passed_time":1.64732294,"remaining_time":14.50290196},
{"learn":[0.444008329],"iteration":102,"passed_time":1.662393553,"remaining_time":14.47734968},
{"learn":[0.4435364447],"iteration":103,"passed_time":1.678113222,"remaining_time":14.45759084},
{"learn":[0.4430381918],"iteration":104,"passed_time":1.693084646,"remaining_time":14.43153103},
{"learn":[0.4426965567],"iteration":105,"passed_time":1.707399031,"remaining_time":14.400139},
{"learn":[0.4421428855],"iteration":106,"passed_time":1.721590182,"remaining_time":14.36803768},
{"learn":[0.441792112],"iteration":107,"passed_time":1.736386377,"remaining_time":14.34126526},
{"learn":[0.4414316956],"iteration":108,"passed_time":1.750454525,"remaining_time":14.3087613},
{"learn":[0.4410982164],"iteration":109,"passed_time":1.766201434,"remaining_time":14.29017523},
{"learn":[0.4406101544],"iteration":110,"passed_time":1.781862724,"remaining_time":14.27095461},
{"learn":[0.4401516112],"iteration":111,"passed_time":1.798407912,"remaining_time":14.25880559},
{"learn":[0.4399556757],"iteration":112,"passed_time":1.813511142,"remaining_time":14.23526002},
{"learn":[0.4395676026],"iteration":113,"passed_time":1.828306278,"remaining_time":14.20946809},
{"learn":[0.4392879624],"iteration":114,"passed_time":1.844221211,"remaining_time":14.19248497},
{"learn":[0.4390997453],"iteration":115,"passed_time":1.858425868,"remaining_time":14.16248679},
{"learn":[0.4387232728],"iteration":116,"passed_time":1.873437848,"remaining_time":14.13885145},
{"learn":[0.4383407542],"iteration":117,"passed_time":1.889492128,"remaining_time":14.12315303},
{"learn":[0.4377695611],"iteration":118,"passed_time":1.904968017,"remaining_time":14.10316658},
{"learn":[0.4373834621],"iteration":119,"passed_time":1.920605851,"remaining_time":14.08444291},
{"learn":[0.4370586515],"iteration":120,"passed_time":1.935849957,"remaining_time":14.06291002},
{"learn":[0.4366318036],"iteration":121,"passed_time":1.951801193,"remaining_time":14.04656924},
{"learn":[0.4362569953],"iteration":122,"passed_time":1.966275101,"remaining_time":14.01970133},
{"learn":[0.4359003524],"iteration":123,"passed_time":1.9811311,"remaining_time":13.99573261},
{"learn":[0.4356063043],"iteration":124,"passed_time":1.997373959,"remaining_time":13.98161771},
{"learn":[0.4352416461],"iteration":125,"passed_time":2.011904878,"remaining_time":13.95559415},
{"learn":[0.4349277004],"iteration":126,"passed_time":2.025436403,"remaining_time":13.92288173},
{"learn":[0.4345814942],"iteration":127,"passed_time":2.040377752,"remaining_time":13.90007344},
{"learn":[0.4342893508],"iteration":128,"passed_time":2.055804568,"remaining_time":13.88066495},
{"learn":[0.4338940237],"iteration":129,"passed_time":2.069635556,"remaining_time":13.85063795},
{"learn":[0.4334811942],"iteration":130,"passed_time":2.084615144,"remaining_time":13.82847756},
{"learn":[0.433236827],"iteration":131,"passed_time":2.099567647,"remaining_time":13.80624786},
{"learn":[0.4329173641],"iteration":132,"passed_time":2.113588834,"remaining_time":13.77805653},
{"learn":[0.4324306902],"iteration":133,"passed_time":2.128446079,"remaining_time":13.75547988},
{"learn":[0.4319609899],"iteration":134,"passed_time":2.142497227,"remaining_time":13.72785261},
{"learn":[0.4315781432],"iteration":135,"passed_time":2.157845696,"remaining_time":13.70866678},
{"learn":[0.4311124564],"iteration":136,"passed_time":2.173755197,"remaining_time":13.69307106},
{"learn":[0.430564503],"iteration":137,"passed_time":2.189173449,"remaining_time":13.67440227},
{"learn":[0.4303178075],"iteration":138,"passed_time":2.204694629,"remaining_time":13.65641781},
{"learn":[0.4301001175],"iteration":139,"passed_time":2.220283631,"remaining_time":13.63888516},
{"learn":[0.4298720134],"iteration":140,"passed_time":2.235173154,"remaining_time":13.61711872},
{"learn":[0.4296793145],"iteration":141,"passed_time":2.25077083,"remaining_time":13.59972797},
{"learn":[0.4292615958],"iteration":142,"passed_time":2.265512302,"remaining_time":13.57723107},
{"learn":[0.4289816159],"iteration":143,"passed_time":2.279601045,"remaining_time":13.55096177},
{"learn":[0.428554727],"iteration":144,"passed_time":2.294331687,"remaining_time":13.52864546},
{"learn":[0.4283093728],"iteration":145,"passed_time":2.308183638,"remaining_time":13.50129334},
{"learn":[0.428021176],"iteration":146,"passed_time":2.322628413,"remaining_time":13.47756487},
{"learn":[0.4275951296],"iteration":147,"passed_time":2.337923018,"remaining_time":13.45885413},
{"learn":[0.4272252901],"iteration":148,"passed_time":2.353548058,"remaining_time":13.44207649},
{"learn":[0.426744356],"iteration":149,"passed_time":2.368694868,"remaining_time":13.42260425},
{"learn":[0.4264994031],"iteration":150,"passed_time":2.384063146,"remaining_time":13.40443451},
{"learn":[0.4262284252],"iteration":151,"passed_time":2.399491644,"remaining_time":13.38663759},
{"learn":[0.4258537629],"iteration":152,"passed_time":2.413858684,"remaining_time":13.36299546},
{"learn":[0.4255553883],"iteration":153,"passed_time":2.429815304,"remaining_time":13.34820615},
{"learn":[0.4251626942],"iteration":154,"passed_time":2.444234938,"remaining_time":13.32502272},
{"learn":[0.4248993198],"iteration":155,"passed_time":2.458921543,"remaining_time":13.30339604},
{"learn":[0.4244802595],"iteration":156,"passed_time":2.47418276,"remaining_time":13.2849431},
{"learn":[0.424099006],"iteration":157,"passed_time":2.490245057,"remaining_time":13.27079961},
{"learn":[0.4238087899],"iteration":158,"passed_time":2.504844974,"remaining_time":13.248897},
{"learn":[0.4234574726],"iteration":159,"passed_time":2.519036052,"remaining_time":13.22493927},
{"learn":[0.4231043674],"iteration":160,"passed_time":2.533058155,"remaining_time":13.20022231},
{"learn":[0.4227996605],"iteration":161,"passed_time":2.547184435,"remaining_time":13.17617627},
{"learn":[0.4224190441],"iteration":162,"passed_time":2.56174104,"remaining_time":13.15446166},
{"learn":[0.4222286989],"iteration":163,"passed_time":2.575968958,"remaining_time":13.13115884},
{"learn":[0.421971537],"iteration":164,"passed_time":2.590679733,"remaining_time":13.11040956},
{"learn":[0.4216518526],"iteration":165,"passed_time":2.605300879,"remaining_time":13.08928273},
{"learn":[0.4214191629],"iteration":166,"passed_time":2.620563238,"remaining_time":13.0714322},
{"learn":[0.4211959912],"iteration":167,"passed_time":2.634522143,"remaining_time":13.04715728},
{"learn":[0.4209768908],"iteration":168,"passed_time":2.649902743,"remaining_time":13.02999514},
{"learn":[0.4204038883],"iteration":169,"passed_time":2.664777752,"remaining_time":13.0103855},
{"learn":[0.4200091355],"iteration":170,"passed_time":2.679930747,"remaining_time":12.99217888},
{"learn":[0.4198007626],"iteration":171,"passed_time":2.694340263,"remaining_time":12.97042871},
{"learn":[0.4195663174],"iteration":172,"passed_time":2.709942838,"remaining_time":12.95446663},
{"learn":[0.4193291552],"iteration":173,"passed_time":2.727275895,"remaining_time":12.9467235},
{"learn":[0.4190864047],"iteration":174,"passed_time":2.741244915,"remaining_time":12.92301174},
{"learn":[0.4185655756],"iteration":175,"passed_time":2.758602622,"remaining_time":12.91527591},
{"learn":[0.4183332725],"iteration":176,"passed_time":2.773556364,"remaining_time":12.8962536},
{"learn":[0.4179478597],"iteration":177,"passed_time":2.789741313,"remaining_time":12.88296269},
{"learn":[0.4175731012],"iteration":178,"passed_time":2.805129452,"remaining_time":12.86598481},
{"learn":[0.4173430857],"iteration":179,"passed_time":2.819364487,"remaining_time":12.84377155},
{"learn":[0.4170270609],"iteration":180,"passed_time":2.835334534,"remaining_time":12.82949715},
{"learn":[0.4164685163],"iteration":181,"passed_time":2.851330721,"remaining_time":12.81532159},
{"learn":[0.4160936359],"iteration":182,"passed_time":2.865823448,"remaining_time":12.79441397},
{"learn":[0.4157125863],"iteration":183,"passed_time":2.879632753,"remaining_time":12.77054525},
{"learn":[0.4154468489],"iteration":184,"passed_time":2.894181234,"remaining_time":12.75004165},
{"learn":[0.4150880465],"iteration":185,"passed_time":2.908934424,"remaining_time":12.73049797},
{"learn":[0.4148725005],"iteration":186,"passed_time":2.924074286,"remaining_time":12.7126866},
{"learn":[0.4145715509],"iteration":187,"passed_time":2.940175992,"remaining_time":12.69905801},
{"learn":[0.4144252024],"iteration":188,"passed_time":2.955538582,"remaining_time":12.6822317},
{"learn":[0.4141967505],"iteration":189,"passed_time":2.96907282,"remaining_time":12.65762623},
{"learn":[0.4138921036],"iteration":190,"passed_time":2.983827888,"remaining_time":12.63830765},
{"learn":[0.4136887672],"iteration":191,"passed_time":2.997213972,"remaining_time":12.61327546},
{"learn":[0.4133537035],"iteration":192,"passed_time":3.011427046,"remaining_time":12.5918219},
{"learn":[0.4131059759],"iteration":193,"passed_time":3.026967208,"remaining_time":12.57595654},
{"learn":[0.4127265338],"iteration":194,"passed_time":3.043428074,"remaining_time":12.56389538},
{"learn":[0.4124653569],"iteration":195,"passed_time":3.058396067,"remaining_time":12.5456655},
{"learn":[0.4122339986],"iteration":196,"passed_time":3.072787189,"remaining_time":12.52511732},
{"learn":[0.4119976705],"iteration":197,"passed_time":3.087284232,"remaining_time":12.50506037},
{"learn":[0.4116800129],"iteration":198,"passed_time":3.102641132,"remaining_time":12.48852034},
{"learn":[0.4113135178],"iteration":199,"passed_time":3.119676814,"remaining_time":12.47870726},
{"learn":[0.4111023292],"iteration":200,"passed_time":3.137316041,"remaining_time":12.47122148},
{"learn":[0.4108684485],"iteration":201,"passed_time":3.153432213,"remaining_time":12.45761835},
{"learn":[0.410453095],"iteration":202,"passed_time":3.16829309,"remaining_time":12.43906203},
{"learn":[0.4101659839],"iteration":203,"passed_time":3.183739109,"remaining_time":12.42282515},
{"learn":[0.4098597087],"iteration":204,"passed_time":3.19878803,"remaining_time":12.40505602},
{"learn":[0.4095682841],"iteration":205,"passed_time":3.213234066,"remaining_time":12.38498955},
{"learn":[0.4092602449],"iteration":206,"passed_time":3.227744707,"remaining_time":12.36522489},
{"learn":[0.4089082446],"iteration":207,"passed_time":3.242085911,"remaining_time":12.34486559},
{"learn":[0.4086380438],"iteration":208,"passed_time":3.257266268,"remaining_time":12.3277398},
{"learn":[0.4082959674],"iteration":209,"passed_time":3.271468125,"remaining_time":12.30695152},
{"learn":[0.4080448853],"iteration":210,"passed_time":3.287444037,"remaining_time":12.29285946},
{"learn":[0.4077885274],"iteration":211,"passed_time":3.30210821,"remaining_time":12.27387391},
{"learn":[0.4074044193],"iteration":212,"passed_time":3.316726016,"remaining_time":12.25475763},
{"learn":[0.4070935714],"iteration":213,"passed_time":3.334966822,"remaining_time":12.24899029},
{"learn":[0.4067737493],"iteration":214,"passed_time":3.349196212,"remaining_time":12.22846059},
{"learn":[0.4064719642],"iteration":215,"passed_time":3.364380347,"remaining_time":12.21145459},
{"learn":[0.4062075919],"iteration":216,"passed_time":3.378554729,"remaining_time":12.1908219},
{"learn":[0.405897941],"iteration":217,"passed_time":3.392431301,"remaining_time":12.16918017},
{"learn":[0.4056272299],"iteration":218,"passed_time":3.407917664,"remaining_time":12.15335021},
{"learn":[0.405353341],"iteration":219,"passed_time":3.42270287,"remaining_time":12.13503745},
{"learn":[0.4050395256],"iteration":220,"passed_time":3.437602864,"remaining_time":12.11716123},
{"learn":[0.4047138001],"iteration":221,"passed_time":3.452865987,"remaining_time":12.10058441},
{"learn":[0.4043684166],"iteration":222,"passed_time":3.468574852,"remaining_time":12.08557246},
{"learn":[0.4041452224],"iteration":223,"passed_time":3.483382424,"remaining_time":12.06743197},
{"learn":[0.4038967604],"iteration":224,"passed_time":3.497418911,"remaining_time":12.04666514},
{"learn":[0.403554235],"iteration":225,"passed_time":3.512297512,"remaining_time":12.02884192},
{"learn":[0.4033491413],"iteration":226,"passed_time":3.525640624,"remaining_time":12.00581587},
{"learn":[0.40306497],"iteration":227,"passed_time":3.540481328,"remaining_time":11.98794555},
{"learn":[0.4028614208],"iteration":228,"passed_time":3.554767498,"remaining_time":11.96823468},
{"learn":[0.4024958165],"iteration":229,"passed_time":3.569641773,"remaining_time":11.95053985},
{"learn":[0.4021998195],"iteration":230,"passed_time":3.583197879,"remaining_time":11.92848125},
{"learn":[0.4017865372],"iteration":231,"passed_time":3.598664798,"remaining_time":11.9128214},
{"learn":[0.4015337043],"iteration":232,"passed_time":3.611653706,"remaining_time":11.88900598},
{"learn":[0.4011408579],"iteration":233,"passed_time":3.626532663,"remaining_time":11.87147017},
{"learn":[0.4009761688],"iteration":234,"passed_time":3.640674517,"remaining_time":11.85155747},
{"learn":[0.4007273306],"iteration":235,"passed_time":3.657739493,"remaining_time":11.84115666},
{"learn":[0.4004555316],"iteration":236,"passed_time":3.674637611,"remaining_time":11.83016244},
{"learn":[0.4002193818],"iteration":237,"passed_time":3.689380276,"remaining_time":11.81221752},
{"learn":[0.3998449639],"iteration":238,"passed_time":3.704150143,"remaining_time":11.79438602},
{"learn":[0.3994702464],"iteration":239,"passed_time":3.719184754,"remaining_time":11.77741839},
{"learn":[0.3992098997],"iteration":240,"passed_time":3.734281,"remaining_time":11.76066091},
{"learn":[0.3989336411],"iteration":241,"passed_time":3.749642209,"remaining_time":11.74474709},
{"learn":[0.3987293289],"iteration":242,"passed_time":3.764354688,"remaining_time":11.72681687},
{"learn":[0.3983119462],"iteration":243,"passed_time":3.779247961,"remaining_time":11.70947319},
{"learn":[0.3980089341],"iteration":244,"passed_time":3.79529956,"remaining_time":11.69571905},
{"learn":[0.3976761528],"iteration":245,"passed_time":3.811682783,"remaining_time":11.68296268},
{"learn":[0.3973970493],"iteration":246,"passed_time":3.825777613,"remaining_time":11.66320058},
{"learn":[0.3970633219],"iteration":247,"passed_time":3.840874743,"remaining_time":11.64652341},
{"learn":[0.3967677244],"iteration":248,"passed_time":3.856538296,"remaining_time":11.63156731},
{"learn":[0.3964744372],"iteration":249,"passed_time":3.873214219,"remaining_time":11.61964266},
{"learn":[0.3960197753],"iteration":250,"passed_time":3.888971958,"remaining_time":11.60494023},
{"learn":[0.3958581647],"iteration":251,"passed_time":3.903535802,"remaining_time":11.58668564},
{"learn":[0.39555794],"iteration":252,"passed_time":3.91920252,"remaining_time":11.57171653},
{"learn":[0.3952772147],"iteration":253,"passed_time":3.935243308,"remaining_time":11.55784058},
{"learn":[0.3951272574],"iteration":254,"passed_time":3.950287611,"remaining_time":11.54103635},
{"learn":[0.3948751528],"iteration":255,"passed_time":3.965800563,"remaining_time":11.52560789},
{"learn":[0.3944960051],"iteration":256,"passed_time":3.981967154,"remaining_time":11.51206846},
{"learn":[0.3941969841],"iteration":257,"passed_time":3.996389086,"remaining_time":11.49349109},
{"learn":[0.3940429197],"iteration":258,"passed_time":4.011287433,"remaining_time":11.47630883},
{"learn":[0.3935490914],"iteration":259,"passed_time":4.028770373,"remaining_time":11.46650029},
{"learn":[0.393352678],"iteration":260,"passed_time":4.043102325,"remaining_time":11.44771118},
{"learn":[0.3929960074],"iteration":261,"passed_time":4.058884064,"remaining_time":11.43303984},
{"learn":[0.3927640221],"iteration":262,"passed_time":4.075138936,"remaining_time":11.41968592},
{"learn":[0.3925478633],"iteration":263,"passed_time":4.090626437,"remaining_time":11.40417067},
{"learn":[0.3923241871],"iteration":264,"passed_time":4.105237602,"remaining_time":11.38622505},
{"learn":[0.3919457386],"iteration":265,"passed_time":4.121310494,"remaining_time":11.37233798},
{"learn":[0.3915486016],"iteration":266,"passed_time":4.135752997,"remaining_time":11.3539586},
{"learn":[0.3910322185],"iteration":267,"passed_time":4.153335734,"remaining_time":11.34418566},
{"learn":[0.390606534],"iteration":268,"passed_time":4.168684356,"remaining_time":11.32828351},
{"learn":[0.3904584137],"iteration":269,"passed_time":4.182738364,"remaining_time":11.30888521},
{"learn":[0.3902508487],"iteration":270,"passed_time":4.197991155,"remaining_time":11.29275111},
{"learn":[0.3900223977],"iteration":271,"passed_time":4.212860514,"remaining_time":11.27559726},
{"learn":[0.3897698421],"iteration":272,"passed_time":4.228172722,"remaining_time":11.25963945},
{"learn":[0.3894393346],"iteration":273,"passed_time":4.242698581,"remaining_time":11.24160281},
{"learn":[0.3891003102],"iteration":274,"passed_time":4.257238656,"remaining_time":11.22362918},
{"learn":[0.3889639318],"iteration":275,"passed_time":4.272026445,"remaining_time":11.20633024},
{"learn":[0.3886983626],"iteration":276,"passed_time":4.286899158,"remaining_time":11.18927109},
{"learn":[0.3884340914],"iteration":277,"passed_time":4.302468862,"remaining_time":11.17403784},
{"learn":[0.3882070594],"iteration":278,"passed_time":4.31695945,"remaining_time":11.15601349},
{"learn":[0.3879480392],"iteration":279,"passed_time":4.332881159,"remaining_time":11.14169441},
{"learn":[0.3876435086],"iteration":280,"passed_time":4.347072778,"remaining_time":11.12293711},
{"learn":[0.3875195357],"iteration":281,"passed_time":4.36162999,"remaining_time":11.10514302},
{"learn":[0.3873697617],"iteration":282,"passed_time":4.37760708,"remaining_time":11.09096918},
{"learn":[0.3871654753],"iteration":283,"passed_time":4.392356632,"remaining_time":11.07368785},
{"learn":[0.3868341903],"iteration":284,"passed_time":4.407097191,"remaining_time":11.05640172},
{"learn":[0.3866360356],"iteration":285,"passed_time":4.421585881,"remaining_time":11.03850461},
{"learn":[0.3864387732],"iteration":286,"passed_time":4.435602189,"remaining_time":11.0194577},
{"learn":[0.3860678357],"iteration":287,"passed_time":4.4500588,"remaining_time":11.00153426},
{"learn":[0.3857538097],"iteration":288,"passed_time":4.464986351,"remaining_time":10.98479341},
{"learn":[0.3852397803],"iteration":289,"passed_time":4.481700141,"remaining_time":10.97243828},
{"learn":[0.3850953029],"iteration":290,"passed_time":4.497557835,"remaining_time":10.95796737},
{"learn":[0.384952913],"iteration":291,"passed_time":4.513165004,"remaining_time":10.94287953},
{"learn":[0.3845548611],"iteration":292,"passed_time":4.52820551,"remaining_time":10.9264208},
{"learn":[0.3843835672],"iteration":293,"passed_time":4.544272154,"remaining_time":10.91243585},
{"learn":[0.3840584173],"iteration":294,"passed_time":4.560647751,"remaining_time":10.89917513},
{"learn":[0.3837487727],"iteration":295,"passed_time":4.575062243,"remaining_time":10.88122912},
{"learn":[0.38345113],"iteration":296,"passed_time":4.590522465,"remaining_time":10.86578213},
{"learn":[0.3832690072],"iteration":297,"passed_time":4.604991803,"remaining_time":10.84800082},
{"learn":[0.3829098792],"iteration":298,"passed_time":4.621472504,"remaining_time":10.83495727},
{"learn":[0.3826456542],"iteration":299,"passed_time":4.635902194,"remaining_time":10.81710512},
{"learn":[0.3822838567],"iteration":300,"passed_time":4.651457782,"remaining_time":10.80189033},
{"learn":[0.3821726038],"iteration":301,"passed_time":4.666365811,"remaining_time":10.78517661},
{"learn":[0.3819905066],"iteration":302,"passed_time":4.681193316,"remaining_time":10.76828957},
{"learn":[0.3815911014],"iteration":303,"passed_time":4.696808013,"remaining_time":10.75321835},
{"learn":[0.3812520302],"iteration":304,"passed_time":4.71126458,"remaining_time":10.73550453},
{"learn":[0.380976419],"iteration":305,"passed_time":4.727559298,"remaining_time":10.72198089},
{"learn":[0.3806265437],"iteration":306,"passed_time":4.741908919,"remaining_time":10.70404847},
{"learn":[0.3803947099],"iteration":307,"passed_time":4.756543085,"remaining_time":10.68677862},
{"learn":[0.3801007297],"iteration":308,"passed_time":4.772137162,"remaining_time":10.67167242},
{"learn":[0.3798552681],"iteration":309,"passed_time":4.787935162,"remaining_time":10.65701697},
{"learn":[0.3796676427],"iteration":310,"passed_time":4.802444156,"remaining_time":10.63949847},
{"learn":[0.3794884134],"iteration":311,"passed_time":4.816906387,"remaining_time":10.62189613},
{"learn":[0.3793496885],"iteration":312,"passed_time":4.832784369,"remaining_time":10.60742128},
{"learn":[0.3790330724],"iteration":313,"passed_time":4.847917661,"remaining_time":10.59131056},
{"learn":[0.3788155606],"iteration":314,"passed_time":4.862562625,"remaining_time":10.57414412},
{"learn":[0.3785455247],"iteration":315,"passed_time":4.877387211,"remaining_time":10.55738244},
{"learn":[0.3783576808],"iteration":316,"passed_time":4.893204697,"remaining_time":10.54277226},
{"learn":[0.3780692142],"iteration":317,"passed_time":4.908439561,"remaining_time":10.52690497},
{"learn":[0.3778211646],"iteration":318,"passed_time":4.923292172,"remaining_time":10.51022561},
{"learn":[0.3775841277],"iteration":319,"passed_time":4.93802492,"remaining_time":10.49330295},
{"learn":[0.3774185987],"iteration":320,"passed_time":4.953057349,"remaining_time":10.47702785},
{"learn":[0.3771853835],"iteration":321,"passed_time":4.967849086,"remaining_time":10.46025367},
{"learn":[0.376855055],"iteration":322,"passed_time":4.982972218,"remaining_time":10.44418635},
{"learn":[0.3765444726],"iteration":323,"passed_time":4.998000136,"remaining_time":10.42792621},
{"learn":[0.37634737],"iteration":324,"passed_time":5.012065255,"remaining_time":10.40967399},
{"learn":[0.3762633556],"iteration":325,"passed_time":5.026688308,"remaining_time":10.39260098},
{"learn":[0.3759015387],"iteration":326,"passed_time":5.042205056,"remaining_time":10.37738227},
{"learn":[0.3757413364],"iteration":327,"passed_time":5.056084953,"remaining_time":10.3588082},
{"learn":[0.3754401101],"iteration":328,"passed_time":5.071027969,"remaining_time":10.3424309},
{"learn":[0.3753047921],"iteration":329,"passed_time":5.084745233,"remaining_time":10.32357365},
{"learn":[0.374845556],"iteration":330,"passed_time":5.099373988,"remaining_time":10.30658972},
{"learn":[0.374376659],"iteration":331,"passed_time":5.115281511,"remaining_time":10.29219292},
{"learn":[0.3741399135],"iteration":332,"passed_time":5.131093795,"remaining_time":10.27759628},
{"learn":[0.3736643924],"iteration":333,"passed_time":5.145458028,"remaining_time":10.26010493},
{"learn":[0.3734935406],"iteration":334,"passed_time":5.160116437,"remaining_time":10.24321621},
{"learn":[0.3733509409],"iteration":335,"passed_time":5.1749839,"remaining_time":10.2267539},
{"learn":[0.3730287855],"iteration":336,"passed_time":5.193055446,"remaining_time":10.21660463},
{"learn":[0.3728427018],"iteration":337,"passed_time":5.209365202,"remaining_time":10.20295788},
{"learn":[0.372663047],"iteration":338,"passed_time":5.225067898,"remaining_time":10.18811174},
{"learn":[0.3724950132],"iteration":339,"passed_time":5.239511836,"remaining_time":10.17081709},
{"learn":[0.3722146862],"iteration":340,"passed_time":5.255609883,"remaining_time":10.15673582},
{"learn":[0.3720189029],"iteration":341,"passed_time":5.269890222,"remaining_time":10.13914552},
{"learn":[0.3718215123],"iteration":342,"passed_time":5.283686488,"remaining_time":10.1206473},
{"learn":[0.3717244028],"iteration":343,"passed_time":5.298024722,"remaining_time":10.10320994},
{"learn":[0.3713369806],"iteration":344,"passed_time":5.313928529,"remaining_time":10.08876286},
{"learn":[0.3710168425],"iteration":345,"passed_time":5.328590461,"remaining_time":10.07196},
{"learn":[0.370688692],"iteration":346,"passed_time":5.34459909,"remaining_time":10.05770376},
{"learn":[0.3704833309],"iteration":347,"passed_time":5.358881967,"remaining_time":10.04020415},
{"learn":[0.3702968348],"iteration":348,"passed_time":5.373872,"remaining_time":10.02404204},
{"learn":[0.3701812529],"iteration":349,"passed_time":5.388868478,"remaining_time":10.0078986},
{"learn":[0.3699552617],"iteration":350,"passed_time":5.404208453,"remaining_time":9.992396826},
{"learn":[0.3697357598],"iteration":351,"passed_time":5.421457442,"remaining_time":9.980410292},
{"learn":[0.369495846],"iteration":352,"passed_time":5.436672706,"remaining_time":9.964666405},
{"learn":[0.3692508423],"iteration":353,"passed_time":5.451391419,"remaining_time":9.94801937},
{"learn":[0.3690319603],"iteration":354,"passed_time":5.466488188,"remaining_time":9.932070088},
{"learn":[0.3687960352],"iteration":355,"passed_time":5.481378709,"remaining_time":9.915752496},
{"learn":[0.3685709552],"iteration":356,"passed_time":5.495977798,"remaining_time":9.898917994},
{"learn":[0.3683358637],"iteration":357,"passed_time":5.512153174,"remaining_time":9.884922731},
{"learn":[0.3682091228],"iteration":358,"passed_time":5.527562587,"remaining_time":9.869547683},
{"learn":[0.367864505],"iteration":359,"passed_time":5.543527779,"remaining_time":9.855160495},
{"learn":[0.3674567487],"iteration":360,"passed_time":5.560401889,"remaining_time":9.842373427},
{"learn":[0.3672298299],"iteration":361,"passed_time":5.576592803,"remaining_time":9.828359691},
{"learn":[0.3671152593],"iteration":362,"passed_time":5.591444733,"remaining_time":9.811984283},
{"learn":[0.3668561811],"iteration":363,"passed_time":5.606631322,"remaining_time":9.79620198},
{"learn":[0.3664585056],"iteration":364,"passed_time":5.621685894,"remaining_time":9.780193268},
{"learn":[0.3662953568],"iteration":365,"passed_time":5.637004018,"remaining_time":9.764646304},
{"learn":[0.3661592829],"iteration":366,"passed_time":5.652530151,"remaining_time":9.749459361},
{"learn":[0.3660376876],"iteration":367,"passed_time":5.667725745,"remaining_time":9.73370291},
{"learn":[0.3657839668],"iteration":368,"passed_time":5.682837378,"remaining_time":9.717805923},
{"learn":[0.3654385275],"iteration":369,"passed_time":5.69798558,"remaining_time":9.701975446},
{"learn":[0.3653154045],"iteration":370,"passed_time":5.712331059,"remaining_time":9.684787699},
{"learn":[0.3649227621],"iteration":371,"passed_time":5.727619743,"remaining_time":9.669207524},
{"learn":[0.3646578286],"iteration":372,"passed_time":5.74324345,"remaining_time":9.654192073},
{"learn":[0.3644148536],"iteration":373,"passed_time":5.757815065,"remaining_time":9.637412382},
{"learn":[0.3643024077],"iteration":374,"passed_time":5.771069369,"remaining_time":9.618448949},
{"learn":[0.3640717845],"iteration":375,"passed_time":5.785589508,"remaining_time":9.60161663},
{"learn":[0.3638155137],"iteration":376,"passed_time":5.801838518,"remaining_time":9.587653573},
{"learn":[0.3635951123],"iteration":377,"passed_time":5.816207635,"remaining_time":9.570585051},
{"learn":[0.3632597605],"iteration":378,"passed_time":5.831528562,"remaining_time":9.555090335},
{"learn":[0.3630923402],"iteration":379,"passed_time":5.845425308,"remaining_time":9.537272871},
{"learn":[0.362871454],"iteration":380,"passed_time":5.859926795,"remaining_time":9.520458494},
{"learn":[0.3625774568],"iteration":381,"passed_time":5.874426027,"remaining_time":9.503652578},
{"learn":[0.3622990629],"iteration":382,"passed_time":5.890344888,"remaining_time":9.489145682},
{"learn":[0.3620641483],"iteration":383,"passed_time":5.905985963,"remaining_time":9.474185815},
{"learn":[0.3618275969],"iteration":384,"passed_time":5.921157487,"remaining_time":9.458472349},
{"learn":[0.3616462521],"iteration":385,"passed_time":5.935594148,"remaining_time":9.441592763},
{"learn":[0.3614559416],"iteration":386,"passed_time":5.949938796,"remaining_time":9.424580057},
{"learn":[0.3610974069],"iteration":387,"passed_time":5.96463694,"remaining_time":9.408138678},
{"learn":[0.3608508442],"iteration":388,"passed_time":5.9794627,"remaining_time":9.391906708},
{"learn":[0.3605973982],"iteration":389,"passed_time":5.994921512,"remaining_time":9.376672109},
{"learn":[0.360480599],"iteration":390,"passed_time":6.009692434,"remaining_time":9.360364942},
{"learn":[0.3603688996],"iteration":391,"passed_time":6.024498916,"remaining_time":9.344120768},
{"learn":[0.3601543043],"iteration":392,"passed_time":6.04050325,"remaining_time":9.329734027},
{"learn":[0.3599563262],"iteration":393,"passed_time":6.054550348,"remaining_time":9.312328708},
{"learn":[0.3597688963],"iteration":394,"passed_time":6.068605163,"remaining_time":9.294952212},
{"learn":[0.3594807899],"iteration":395,"passed_time":6.083472764,"remaining_time":9.278832195},
{"learn":[0.3592856909],"iteration":396,"passed_time":6.098484308,"remaining_time":9.262937123},
{"learn":[0.3591357931],"iteration":397,"passed_time":6.113559835,"remaining_time":9.247143268},
{"learn":[0.3589707201],"iteration":398,"passed_time":6.129067454,"remaining_time":9.232003859},
{"learn":[0.3586213308],"iteration":399,"passed_time":6.143777768,"remaining_time":9.215666652},
{"learn":[0.3583948052],"iteration":400,"passed_time":6.158264934,"remaining_time":9.199004229},
{"learn":[0.3581932129],"iteration":401,"passed_time":6.173851229,"remaining_time":9.183987649},
{"learn":[0.3579504147],"iteration":402,"passed_time":6.188383262,"remaining_time":9.167406471},
{"learn":[0.3578101964],"iteration":403,"passed_time":6.20340177,"remaining_time":9.151553106},
{"learn":[0.35764069],"iteration":404,"passed_time":6.218866864,"remaining_time":9.136359961},
{"learn":[0.357386697],"iteration":405,"passed_time":6.236173573,"remaining_time":9.123859859},
{"learn":[0.3571162055],"iteration":406,"passed_time":6.252266421,"remaining_time":9.109567537},
{"learn":[0.3568399984],"iteration":407,"passed_time":6.267953681,"remaining_time":9.094677891},
{"learn":[0.3567376082],"iteration":408,"passed_time":6.28319251,"remaining_time":9.079136365},
{"learn":[0.3565741032],"iteration":409,"passed_time":6.298546378,"remaining_time":9.063761861},
{"learn":[0.3562754218],"iteration":410,"passed_time":6.313984973,"remaining_time":9.048508878},
{"learn":[0.3558779116],"iteration":411,"passed_time":6.32947443,"remaining_time":9.033327585},
{"learn":[0.3557001104],"iteration":412,"passed_time":6.344261987,"remaining_time":9.017147183},
{"learn":[0.3555126622],"iteration":413,"passed_time":6.358691626,"remaining_time":9.00046689},
{"learn":[0.3553130505],"iteration":414,"passed_time":6.373390998,"remaining_time":8.984177672},
{"learn":[0.355152584],"iteration":415,"passed_time":6.388115436,"remaining_time":8.967931285},
{"learn":[0.3548724667],"iteration":416,"passed_time":6.403622665,"remaining_time":8.952786604},
{"learn":[0.35468676],"iteration":417,"passed_time":6.417966804,"remaining_time":8.936020765},
{"learn":[0.3545165216],"iteration":418,"passed_time":6.433229046,"remaining_time":8.920539561},
{"learn":[0.3542451516],"iteration":419,"passed_time":6.450016366,"remaining_time":8.907165458},
{"learn":[0.3539607585],"iteration":420,"passed_time":6.464662687,"remaining_time":8.890830631},
{"learn":[0.3537652864],"iteration":421,"passed_time":6.479494262,"remaining_time":8.874757544},
{"learn":[0.3535461479],"iteration":422,"passed_time":6.49451741,"remaining_time":8.858951644},
{"learn":[0.3533683445],"iteration":423,"passed_time":6.509651747,"remaining_time":8.843300486},
{"learn":[0.3532092676],"iteration":424,"passed_time":6.524169862,"remaining_time":8.826818049},
{"learn":[0.3530049694],"iteration":425,"passed_time":6.538634726,"remaining_time":8.810273081},
{"learn":[0.3527913039],"iteration":426,"passed_time":6.554533788,"remaining_time":8.795662437},
{"learn":[0.352622552],"iteration":427,"passed_time":6.569796569,"remaining_time":8.780195414},
{"learn":[0.3523714641],"iteration":428,"passed_time":6.58620437,"remaining_time":8.766253369},
{"learn":[0.3521693118],"iteration":429,"passed_time":6.601607975,"remaining_time":8.750968712},
{"learn":[0.3518909692],"iteration":430,"passed_time":6.617849372,"remaining_time":8.736789542},
{"learn":[0.35171184],"iteration":431,"passed_time":6.632648093,"remaining_time":8.720703974},
{"learn":[0.3515209586],"iteration":432,"passed_time":6.648877813,"remaining_time":8.706498198},
{"learn":[0.3511686809],"iteration":433,"passed_time":6.665923785,"remaining_time":8.693347609},
{"learn":[0.3510222968],"iteration":434,"passed_time":6.680383133,"remaining_time":8.676819472},
{"learn":[0.3507758162],"iteration":435,"passed_time":6.695919703,"remaining_time":8.661694294},
{"learn":[0.3506730272],"iteration":436,"passed_time":6.710030456,"remaining_time":8.644730313},
{"learn":[0.3504165371],"iteration":437,"passed_time":6.724934566,"remaining_time":8.628797319},
{"learn":[0.3502207368],"iteration":438,"passed_time":6.740500545,"remaining_time":8.61371482},
{"learn":[0.3499123881],"iteration":439,"passed_time":6.756595176,"remaining_time":8.599302951},
{"learn":[0.3497001856],"iteration":440,"passed_time":6.771526275,"remaining_time":8.58340859},
{"learn":[0.3493475972],"iteration":441,"passed_time":6.788115874,"remaining_time":8.569612348},
{"learn":[0.3490789434],"iteration":442,"passed_time":6.80430869,"remaining_time":8.555304605},
{"learn":[0.3487595626],"iteration":443,"passed_time":6.820009912,"remaining_time":8.540372773},
{"learn":[0.3485252744],"iteration":444,"passed_time":6.835357001,"remaining_time":8.524995811},
{"learn":[0.3482687298],"iteration":445,"passed_time":6.851771182,"remaining_time":8.510944473},
{"learn":[0.3480732062],"iteration":446,"passed_time":6.866798961,"remaining_time":8.495167395},
{"learn":[0.347826501],"iteration":447,"passed_time":6.883792603,"remaining_time":8.481815886},
{"learn":[0.3477088858],"iteration":448,"passed_time":6.899396865,"remaining_time":8.466743146},
{"learn":[0.347579109],"iteration":449,"passed_time":6.91414667,"remaining_time":8.450623708},
{"learn":[0.3473931767],"iteration":450,"passed_time":6.929118149,"remaining_time":8.434780186},
{"learn":[0.3471323859],"iteration":451,"passed_time":6.945598491,"remaining_time":8.420769852},
{"learn":[0.3468958017],"iteration":452,"passed_time":6.961068051,"remaining_time":8.405528088},
{"learn":[0.3467208264],"iteration":453,"passed_time":6.975395376,"remaining_time":8.38891162},
{"learn":[0.3464675244],"iteration":454,"passed_time":6.99100631,"remaining_time":8.373842723},
{"learn":[0.3461844674],"iteration":455,"passed_time":7.007151905,"remaining_time":8.359409291},
{"learn":[0.3460522914],"iteration":456,"passed_time":7.02312646,"remaining_time":8.344765137},
{"learn":[0.3458066002],"iteration":457,"passed_time":7.03817852,"remaining_time":8.329023488},
{"learn":[0.3455553589],"iteration":458,"passed_time":7.052957633,"remaining_time":8.312963136},
{"learn":[0.3453338914],"iteration":459,"passed_time":7.068722223,"remaining_time":8.298065218},
{"learn":[0.3451783277],"iteration":460,"passed_time":7.082951882,"remaining_time":8.281368904},
{"learn":[0.3448786402],"iteration":461,"passed_time":7.098586331,"remaining_time":8.266319148},
{"learn":[0.3447340239],"iteration":462,"passed_time":7.113137526,"remaining_time":8.250010478},
{"learn":[0.3444009655],"iteration":463,"passed_time":7.128193568,"remaining_time":8.23429257},
{"learn":[0.3441147634],"iteration":464,"passed_time":7.143309034,"remaining_time":8.218645878},
{"learn":[0.3438622669],"iteration":465,"passed_time":7.157845078,"remaining_time":8.202337493},
{"learn":[0.343624734],"iteration":466,"passed_time":7.172786999,"remaining_time":8.186499936},
{"learn":[0.3434722017],"iteration":467,"passed_time":7.18867092,"remaining_time":8.171737029},
{"learn":[0.3432533881],"iteration":468,"passed_time":7.204028315,"remaining_time":8.156373209},
{"learn":[0.3429897722],"iteration":469,"passed_time":7.218512432,"remaining_time":8.140024658},
{"learn":[0.3427839658],"iteration":470,"passed_time":7.233639914,"remaining_time":8.124406612},
{"learn":[0.3426395583],"iteration":471,"passed_time":7.248630618,"remaining_time":8.10863764},
{"learn":[0.3424741199],"iteration":472,"passed_time":7.264944,"remaining_time":8.09434564},
{"learn":[0.3423265328],"iteration":473,"passed_time":7.278816628,"remaining_time":8.077336596},
{"learn":[0.3421630724],"iteration":474,"passed_time":7.294654124,"remaining_time":8.062512453},
{"learn":[0.3419053227],"iteration":475,"passed_time":7.309830078,"remaining_time":8.0469558},
{"learn":[0.3416808379],"iteration":476,"passed_time":7.324972797,"remaining_time":8.031364304},
{"learn":[0.3414027184],"iteration":477,"passed_time":7.341758484,"remaining_time":8.017568889},
{"learn":[0.3412523395],"iteration":478,"passed_time":7.355880557,"remaining_time":8.000863821},
{"learn":[0.3411199925],"iteration":479,"passed_time":7.370851864,"remaining_time":7.985089519},
{"learn":[0.3406934921],"iteration":480,"passed_time":7.387477694,"remaining_time":7.97110379},
{"learn":[0.3405047027],"iteration":481,"passed_time":7.402763368,"remaining_time":7.955666856},
{"learn":[0.3403014484],"iteration":482,"passed_time":7.419389335,"remaining_time":7.941665189},
{"learn":[0.3401008911],"iteration":483,"passed_time":7.435093209,"remaining_time":7.92666962},
{"learn":[0.3398340768],"iteration":484,"passed_time":7.450486778,"remaining_time":7.91134163},
{"learn":[0.3396362454],"iteration":485,"passed_time":7.4663522,"remaining_time":7.896512409},
{"learn":[0.3395496939],"iteration":486,"passed_time":7.480839933,"remaining_time":7.880227691},
{"learn":[0.3393749529],"iteration":487,"passed_time":7.496145004,"remaining_time":7.864807873},
{"learn":[0.339115708],"iteration":488,"passed_time":7.51159782,"remaining_time":7.849542916},
{"learn":[0.3389738177],"iteration":489,"passed_time":7.52593975,"remaining_time":7.833120965},
{"learn":[0.338799394],"iteration":490,"passed_time":7.54098797,"remaining_time":7.817439667},
{"learn":[0.3386263859],"iteration":491,"passed_time":7.555703151,"remaining_time":7.801417075},
{"learn":[0.3384433841],"iteration":492,"passed_time":7.571148075,"remaining_time":7.786150252},
{"learn":[0.3381798512],"iteration":493,"passed_time":7.586389319,"remaining_time":7.77067408},
{"learn":[0.3378946397],"iteration":494,"passed_time":7.602826814,"remaining_time":7.756419275},
{"learn":[0.3376812415],"iteration":495,"passed_time":7.61866228,"remaining_time":7.741543929},
{"learn":[0.3375232312],"iteration":496,"passed_time":7.634247058,"remaining_time":7.726411007},
{"learn":[0.3373285979],"iteration":497,"passed_time":7.648965808,"remaining_time":7.710403285},
{"learn":[0.3372257948],"iteration":498,"passed_time":7.6633046,"remaining_time":7.694019247},
{"learn":[0.3370558037],"iteration":499,"passed_time":7.677968414,"remaining_time":7.677968414},
{"learn":[0.3368478844],"iteration":500,"passed_time":7.692627382,"remaining_time":7.661918291},
{"learn":[0.3366421063],"iteration":501,"passed_time":7.708093452,"remaining_time":7.646674381},
{"learn":[0.3365602458],"iteration":502,"passed_time":7.722483972,"remaining_time":7.630366867},
{"learn":[0.3363962905],"iteration":503,"passed_time":7.737816226,"remaining_time":7.614993746},
{"learn":[0.3362133661],"iteration":504,"passed_time":7.753174133,"remaining_time":7.599645932},
{"learn":[0.3360469155],"iteration":505,"passed_time":7.769385205,"remaining_time":7.585131011},
{"learn":[0.3358445678],"iteration":506,"passed_time":7.784836572,"remaining_time":7.56987067},
{"learn":[0.335652592],"iteration":507,"passed_time":7.800920327,"remaining_time":7.555222049},
{"learn":[0.3353490283],"iteration":508,"passed_time":7.816364409,"remaining_time":7.539950737},
{"learn":[0.3350477061],"iteration":509,"passed_time":7.832278821,"remaining_time":7.525130632},
{"learn":[0.334731186],"iteration":510,"passed_time":7.848875228,"remaining_time":7.510958878},
{"learn":[0.3346048646],"iteration":511,"passed_time":7.863819985,"remaining_time":7.495203423},
{"learn":[0.3344260209],"iteration":512,"passed_time":7.878174045,"remaining_time":7.47889037},
{"learn":[0.3342406359],"iteration":513,"passed_time":7.893198735,"remaining_time":7.463219037},
{"learn":[0.3340564872],"iteration":514,"passed_time":7.90795947,"remaining_time":7.447301637},
{"learn":[0.333846251],"iteration":515,"passed_time":7.923842293,"remaining_time":7.432441221},
{"learn":[0.3336847532],"iteration":516,"passed_time":7.939076614,"remaining_time":7.416970996},
{"learn":[0.333549523],"iteration":517,"passed_time":7.953663016,"remaining_time":7.400898791},
{"learn":[0.3332766548],"iteration":518,"passed_time":7.96814737,"remaining_time":7.384737736},
{"learn":[0.332959313],"iteration":519,"passed_time":7.983566504,"remaining_time":7.369446004},
{"learn":[0.3327359627],"iteration":520,"passed_time":8.000058482,"remaining_time":7.35514014},
{"learn":[0.3325197904],"iteration":521,"passed_time":8.015301212,"remaining_time":7.339681953},
{"learn":[0.332308325],"iteration":522,"passed_time":8.029947589,"remaining_time":7.323680688},
{"learn":[0.3321180875],"iteration":523,"passed_time":8.044731969,"remaining_time":7.307809957},
{"learn":[0.3318334625],"iteration":524,"passed_time":8.061384781,"remaining_time":7.293633849},
{"learn":[0.3315623512],"iteration":525,"passed_time":8.077420083,"remaining_time":7.278891862},
{"learn":[0.3313307992],"iteration":526,"passed_time":8.094317775,"remaining_time":7.26491899},
{"learn":[0.3312423618],"iteration":527,"passed_time":8.109491308,"remaining_time":7.249393745},
{"learn":[0.3310031272],"iteration":528,"passed_time":8.126253103,"remaining_time":7.235283954},
{"learn":[0.3307225566],"iteration":529,"passed_time":8.141609361,"remaining_time":7.219917735},
{"learn":[0.3306187517],"iteration":530,"passed_time":8.156130134,"remaining_time":7.203813621},
{"learn":[0.3303843776],"iteration":531,"passed_time":8.171365712,"remaining_time":7.188344273},
{"learn":[0.3302578605],"iteration":532,"passed_time":8.186935526,"remaining_time":7.17316865},
{"learn":[0.3300777283],"iteration":533,"passed_time":8.201409786,"remaining_time":7.157035506},
{"learn":[0.3297771355],"iteration":534,"passed_time":8.219119552,"remaining_time":7.143720732},
{"learn":[0.3295984547],"iteration":535,"passed_time":8.234511097,"remaining_time":7.128382741},
{"learn":[0.3294454072],"iteration":536,"passed_time":8.249279842,"remaining_time":7.112507573},
{"learn":[0.3292583739],"iteration":537,"passed_time":8.263462893,"remaining_time":7.096133563},
{"learn":[0.3291125623],"iteration":538,"passed_time":8.278848474,"remaining_time":7.080796191},
{"learn":[0.3290529333],"iteration":539,"passed_time":8.291147026,"remaining_time":7.062828948},
{"learn":[0.3287321941],"iteration":540,"passed_time":8.307036287,"remaining_time":7.047929123},
{"learn":[0.3285150896],"iteration":541,"passed_time":8.323386835,"remaining_time":7.033415444},
{"learn":[0.3283090213],"iteration":542,"passed_time":8.339374036,"remaining_time":7.018589198},
{"learn":[0.3281100197],"iteration":543,"passed_time":8.354927937,"remaining_time":7.003395477},
{"learn":[0.3279736099],"iteration":544,"passed_time":8.369754246,"remaining_time":6.987592994},
{"learn":[0.3278095965],"iteration":545,"passed_time":8.385578971,"remaining_time":6.972624273},
{"learn":[0.3275492613],"iteration":546,"passed_time":8.401854782,"remaining_time":6.95802599},
{"learn":[0.3274523772],"iteration":547,"passed_time":8.416157853,"remaining_time":6.941794434},
{"learn":[0.3271379059],"iteration":548,"passed_time":8.431980377,"remaining_time":6.926818124},
{"learn":[0.3269265616],"iteration":549,"passed_time":8.447642848,"remaining_time":6.911707784},
{"learn":[0.3267397848],"iteration":550,"passed_time":8.464601556,"remaining_time":6.897651722},
{"learn":[0.3264807579],"iteration":551,"passed_time":8.481918261,"remaining_time":6.88387569},
{"learn":[0.3262960266],"iteration":552,"passed_time":8.497775719,"remaining_time":6.868907317},
{"learn":[0.3260197569],"iteration":553,"passed_time":8.514658013,"remaining_time":6.854760783},
{"learn":[0.3258609291],"iteration":554,"passed_time":8.528666832,"remaining_time":6.838300433},
{"learn":[0.3256651174],"iteration":555,"passed_time":8.544056762,"remaining_time":6.822951803},
{"learn":[0.3254186082],"iteration":556,"passed_time":8.557765443,"remaining_time":6.806265873},
{"learn":[0.3252055515],"iteration":557,"passed_time":8.572359391,"remaining_time":6.790291847},
{"learn":[0.3250692647],"iteration":558,"passed_time":8.586740532,"remaining_time":6.774154874},
{"learn":[0.3249509127],"iteration":559,"passed_time":8.601402152,"remaining_time":6.758244548},
{"learn":[0.3248002284],"iteration":560,"passed_time":8.615982879,"remaining_time":6.742275372},
{"learn":[0.3246615334],"iteration":561,"passed_time":8.629821355,"remaining_time":6.725732657},
{"learn":[0.3244346887],"iteration":562,"passed_time":8.644799033,"remaining_time":6.710083797},
{"learn":[0.3243022259],"iteration":563,"passed_time":8.659526939,"remaining_time":6.69424423},
{"learn":[0.3239915905],"iteration":564,"passed_time":8.674723098,"remaining_time":6.678769111},
{"learn":[0.3237187796],"iteration":565,"passed_time":8.691679291,"remaining_time":6.664644544},
{"learn":[0.3235094417],"iteration":566,"passed_time":8.708565187,"remaining_time":6.650456307},
{"learn":[0.3234017651],"iteration":567,"passed_time":8.722367529,"remaining_time":6.633913332},
{"learn":[0.3230279642],"iteration":568,"passed_time":8.738138436,"remaining_time":6.618871118},
{"learn":[0.3228292016],"iteration":569,"passed_time":8.752328966,"remaining_time":6.602634132},
{"learn":[0.32256118],"iteration":570,"passed_time":8.767562826,"remaining_time":6.587188183},
{"learn":[0.3223826596],"iteration":571,"passed_time":8.782628667,"remaining_time":6.571617254},
{"learn":[0.3221622328],"iteration":572,"passed_time":8.796623416,"remaining_time":6.55524991},
{"learn":[0.3219939789],"iteration":573,"passed_time":8.811567103,"remaining_time":6.539595098},
{"learn":[0.3218708282],"iteration":574,"passed_time":8.825673174,"remaining_time":6.523323651},
{"learn":[0.3217797744],"iteration":575,"passed_time":8.840445367,"remaining_time":6.507550062},
{"learn":[0.3215191151],"iteration":576,"passed_time":8.856956613,"remaining_time":6.493054848},
{"learn":[0.3212528732],"iteration":577,"passed_time":8.8724674,"remaining_time":6.47782222},
{"learn":[0.3211083855],"iteration":578,"passed_time":8.887811179,"remaining_time":6.462467196},
{"learn":[0.3208678946],"iteration":579,"passed_time":8.903360909,"remaining_time":6.447261348},
{"learn":[0.3206435673],"iteration":580,"passed_time":8.918837885,"remaining_time":6.432001848},
{"learn":[0.3204473827],"iteration":581,"passed_time":8.934307399,"remaining_time":6.416736242},
{"learn":[0.3202934362],"iteration":582,"passed_time":8.948912334,"remaining_time":6.400851532},
{"learn":[0.3201231521],"iteration":583,"passed_time":8.965278396,"remaining_time":6.386225707},
{"learn":[0.3198922155],"iteration":584,"passed_time":8.981649229,"remaining_time":6.371597316},
{"learn":[0.3196070079],"iteration":585,"passed_time":8.997749252,"remaining_time":6.356771656},
{"learn":[0.3194527914],"iteration":586,"passed_time":9.012489754,"remaining_time":6.340985125},
{"learn":[0.3192646508],"iteration":587,"passed_time":9.027316037,"remaining_time":6.325262257},
{"learn":[0.31911776],"iteration":588,"passed_time":9.042569435,"remaining_time":6.309840471},
{"learn":[0.3189901547],"iteration":589,"passed_time":9.056906783,"remaining_time":6.29378268},
{"learn":[0.318845958],"iteration":590,"passed_time":9.071022398,"remaining_time":6.27757726},
{"learn":[0.3186269684],"iteration":591,"passed_time":9.086812557,"remaining_time":6.262532978},
{"learn":[0.3184888748],"iteration":592,"passed_time":9.101391258,"remaining_time":6.246654708},
{"learn":[0.3182856461],"iteration":593,"passed_time":9.117056355,"remaining_time":6.231523367},
{"learn":[0.3181087042],"iteration":594,"passed_time":9.133652089,"remaining_time":6.217023691},
{"learn":[0.3179920397],"iteration":595,"passed_time":9.149004496,"remaining_time":6.201674189},
{"learn":[0.3177389305],"iteration":596,"passed_time":9.164923449,"remaining_time":6.186707119},
{"learn":[0.3175946852],"iteration":597,"passed_time":9.180424925,"remaining_time":6.17145622},
{"learn":[0.3172708864],"iteration":598,"passed_time":9.19542243,"remaining_time":6.155867103},
{"learn":[0.3171114877],"iteration":599,"passed_time":9.210288412,"remaining_time":6.140192275},
{"learn":[0.3169175245],"iteration":600,"passed_time":9.224905505,"remaining_time":6.124354903},
{"learn":[0.3167834113],"iteration":601,"passed_time":9.239232363,"remaining_time":6.108329702},
{"learn":[0.3165949166],"iteration":602,"passed_time":9.253666618,"remaining_time":6.092380841},
{"learn":[0.3164917535],"iteration":603,"passed_time":9.26861163,"remaining_time":6.076771863},
{"learn":[0.3164131317],"iteration":604,"passed_time":9.283248872,"remaining_time":6.06096414},
{"learn":[0.3162173102],"iteration":605,"passed_time":9.298360738,"remaining_time":6.045468863},
{"learn":[0.3160254635],"iteration":606,"passed_time":9.313423168,"remaining_time":6.029942842},
{"learn":[0.3159241439],"iteration":607,"passed_time":9.328818161,"remaining_time":6.014632762},
{"learn":[0.3156631497],"iteration":608,"passed_time":9.345953578,"remaining_time":6.000439818},
{"learn":[0.3154243951],"iteration":609,"passed_time":9.360756598,"remaining_time":5.984746022},
{"learn":[0.3151286654],"iteration":610,"passed_time":9.376977422,"remaining_time":5.969957802},
{"learn":[0.3149385525],"iteration":611,"passed_time":9.391165953,"remaining_time":5.953876454},
{"learn":[0.3148167503],"iteration":612,"passed_time":9.406058287,"remaining_time":5.938245607},
{"learn":[0.3147567546],"iteration":613,"passed_time":9.419906215,"remaining_time":5.921960584},
{"learn":[0.314596783],"iteration":614,"passed_time":9.435895138,"remaining_time":5.907023786},
{"learn":[0.3144619052],"iteration":615,"passed_time":9.451696621,"remaining_time":5.891966725},
{"learn":[0.3143092744],"iteration":616,"passed_time":9.467570902,"remaining_time":5.87695244},
{"learn":[0.314129055],"iteration":617,"passed_time":9.48446739,"remaining_time":5.862567221},
{"learn":[0.31388835],"iteration":618,"passed_time":9.502389807,"remaining_time":5.848805358},
{"learn":[0.3136682771],"iteration":619,"passed_time":9.521490937,"remaining_time":5.83575251},
{"learn":[0.3134566201],"iteration":620,"passed_time":9.538332005,"remaining_time":5.821300853},
{"learn":[0.3134112842],"iteration":621,"passed_time":9.552964744,"remaining_time":5.805499475},
{"learn":[0.3132622755],"iteration":622,"passed_time":9.569597879,"remaining_time":5.79091236},
{"learn":[0.3131141339],"iteration":623,"passed_time":9.584582736,"remaining_time":5.775325495},
{"learn":[0.3129777369],"iteration":624,"passed_time":9.599931745,"remaining_time":5.759959047},
{"learn":[0.3126494699],"iteration":625,"passed_time":9.616813318,"remaining_time":5.745508276},
{"learn":[0.3124722995],"iteration":626,"passed_time":9.6321624,"remaining_time":5.730138078},
{"learn":[0.3123276779],"iteration":627,"passed_time":9.646058782,"remaining_time":5.713907431},
{"learn":[0.3121964157],"iteration":628,"passed_time":9.661552204,"remaining_time":5.698626181},
{"learn":[0.3120062305],"iteration":629,"passed_time":9.678604465,"remaining_time":5.684259765},
{"learn":[0.3116517865],"iteration":630,"passed_time":9.695284644,"remaining_time":5.669667249},
{"learn":[0.311359221],"iteration":631,"passed_time":9.710818424,"remaining_time":5.654400601},
{"learn":[0.3111674873],"iteration":632,"passed_time":9.726738319,"remaining_time":5.639356971},
{"learn":[0.3109265319],"iteration":633,"passed_time":9.742605956,"remaining_time":5.62428041},
{"learn":[0.3108378824],"iteration":634,"passed_time":9.756843033,"remaining_time":5.608264106},
{"learn":[0.310716818],"iteration":635,"passed_time":9.772536097,"remaining_time":5.593086697},
{"learn":[0.3105284505],"iteration":636,"passed_time":9.7881647,"remaining_time":5.577870936},
{"learn":[0.3102687346],"iteration":637,"passed_time":9.803985494,"remaining_time":5.562762929},
{"learn":[0.3101672509],"iteration":638,"passed_time":9.818384505,"remaining_time":5.546849462},
{"learn":[0.3100024916],"iteration":639,"passed_time":9.834343759,"remaining_time":5.531818365},
{"learn":[0.3098240776],"iteration":640,"passed_time":9.850091153,"remaining_time":5.516665716},
{"learn":[0.3097316428],"iteration":641,"passed_time":9.864766404,"remaining_time":5.500913353},
{"learn":[0.3095628245],"iteration":642,"passed_time":9.879598706,"remaining_time":5.485251537},
{"learn":[0.3092960853],"iteration":643,"passed_time":9.895433482,"remaining_time":5.470146459},
{"learn":[0.309068272],"iteration":644,"passed_time":9.911802667,"remaining_time":5.455333251},
{"learn":[0.3088780492],"iteration":645,"passed_time":9.926903315,"remaining_time":5.439820083},
{"learn":[0.3086786906],"iteration":646,"passed_time":9.940361319,"remaining_time":5.423411972},
{"learn":[0.3085858112],"iteration":647,"passed_time":9.954862214,"remaining_time":5.407579474},
{"learn":[0.3083961535],"iteration":648,"passed_time":9.972233501,"remaining_time":5.39330348},
{"learn":[0.3081394727],"iteration":649,"passed_time":9.987101089,"remaining_time":5.377669817},
{"learn":[0.307873037],"iteration":650,"passed_time":10.00130633,"remaining_time":5.361683423},
{"learn":[0.3077294357],"iteration":651,"passed_time":10.01545761,"remaining_time":5.345673694},
{"learn":[0.3075950789],"iteration":652,"passed_time":10.03136982,"remaining_time":5.330605404},
{"learn":[0.3074152468],"iteration":653,"passed_time":10.04781266,"remaining_time":5.315815261},
{"learn":[0.3071810665],"iteration":654,"passed_time":10.06324241,"remaining_time":5.30048646},
{"learn":[0.307084312],"iteration":655,"passed_time":10.07731949,"remaining_time":5.284448024},
{"learn":[0.306816259],"iteration":656,"passed_time":10.09273645,"remaining_time":5.269115073},
{"learn":[0.3067275891],"iteration":657,"passed_time":10.10772117,"remaining_time":5.253557205},
{"learn":[0.3065629681],"iteration":658,"passed_time":10.12153249,"remaining_time":5.2373939},
{"learn":[0.3064005376],"iteration":659,"passed_time":10.1367181,"remaining_time":5.221945686},
{"learn":[0.3060307632],"iteration":660,"passed_time":10.15327584,"remaining_time":5.207201983},
{"learn":[0.3059059247],"iteration":661,"passed_time":10.1673765,"remaining_time":5.191198273},
{"learn":[0.3058033001],"iteration":662,"passed_time":10.18253359,"remaining_time":5.175737283},
{"learn":[0.3056854434],"iteration":663,"passed_time":10.19862999,"remaining_time":5.160752527},
{"learn":[0.3053597777],"iteration":664,"passed_time":10.21500226,"remaining_time":5.145903395},
{"learn":[0.3052813689],"iteration":665,"passed_time":10.23023453,"remaining_time":5.130477978},
{"learn":[0.3050558908],"iteration":666,"passed_time":10.24551887,"remaining_time":5.115079135},
{"learn":[0.304874164],"iteration":667,"passed_time":10.26129816,"remaining_time":5.099926629},
{"learn":[0.3047328382],"iteration":668,"passed_time":10.27722104,"remaining_time":5.084843295},
{"learn":[0.3045980915],"iteration":669,"passed_time":10.29349536,"remaining_time":5.069930552},
{"learn":[0.3043976225],"iteration":670,"passed_time":10.30928342,"remaining_time":5.054775331},
{"learn":[0.3042677381],"iteration":671,"passed_time":10.32434488,"remaining_time":5.039263573},
{"learn":[0.3041721144],"iteration":672,"passed_time":10.33913568,"remaining_time":5.023621643},
{"learn":[0.3039817363],"iteration":673,"passed_time":10.35561353,"remaining_time":5.008798235},
{"learn":[0.3038583738],"iteration":674,"passed_time":10.37093856,"remaining_time":4.993414864},
{"learn":[0.3036965348],"iteration":675,"passed_time":10.38629568,"remaining_time":4.978047042},
{"learn":[0.3034420671],"iteration":676,"passed_time":10.40150274,"remaining_time":4.962607657},
{"learn":[0.3033291383],"iteration":677,"passed_time":10.41666771,"remaining_time":4.947148973},
{"learn":[0.3032264408],"iteration":678,"passed_time":10.43227682,"remaining_time":4.931901119},
{"learn":[0.3030197561],"iteration":679,"passed_time":10.4471088,"remaining_time":4.916286495},
{"learn":[0.3026280545],"iteration":680,"passed_time":10.46306715,"remaining_time":4.901201791},
{"learn":[0.3025217107],"iteration":681,"passed_time":10.47913311,"remaining_time":4.886164707},
{"learn":[0.3023241635],"iteration":682,"passed_time":10.4937417,"remaining_time":4.870448197},
{"learn":[0.3021770684],"iteration":683,"passed_time":10.50861847,"remaining_time":4.854858823},
{"learn":[0.3020322487],"iteration":684,"passed_time":10.52341177,"remaining_time":4.839233148},
{"learn":[0.3019220945],"iteration":685,"passed_time":10.53829433,"remaining_time":4.823650756},
{"learn":[0.3017290599],"iteration":686,"passed_time":10.55296591,"remaining_time":4.807974281},
{"learn":[0.301588841],"iteration":687,"passed_time":10.56736088,"remaining_time":4.792175283},
{"learn":[0.3015222026],"iteration":688,"passed_time":10.58201228,"remaining_time":4.77649611},
{"learn":[0.3013941394],"iteration":689,"passed_time":10.59677029,"remaining_time":4.760867812},
{"learn":[0.301119102],"iteration":690,"passed_time":10.61290423,"remaining_time":4.745857318},
{"learn":[0.3009694947],"iteration":691,"passed_time":10.62898109,"remaining_time":4.730818174},
{"learn":[0.3008584605],"iteration":692,"passed_time":10.64538686,"remaining_time":4.715921742},
{"learn":[0.3006847342],"iteration":693,"passed_time":10.66055864,"remaining_time":4.700476864},
{"learn":[0.3005800909],"iteration":694,"passed_time":10.67435983,"remaining_time":4.684431291},
{"learn":[0.3003691323],"iteration":695,"passed_time":10.68976599,"remaining_time":4.669093192},
{"learn":[0.3001162639],"iteration":696,"passed_time":10.70605122,"remaining_time":4.654137045},
{"learn":[0.299969458],"iteration":697,"passed_time":10.7222535,"remaining_time":4.639141201},
{"learn":[0.2998291166],"iteration":698,"passed_time":10.73781429,"remaining_time":4.623865668},
{"learn":[0.2996992189],"iteration":699,"passed_time":10.75182998,"remaining_time":4.607927134},
{"learn":[0.2994762032],"iteration":700,"passed_time":10.7667688,"remaining_time":4.592387835},
{"learn":[0.2990984285],"iteration":701,"passed_time":10.7829467,"remaining_time":4.577376234},
{"learn":[0.2990121583],"iteration":702,"passed_time":10.79767202,"remaining_time":4.561747639},
{"learn":[0.2988615185],"iteration":703,"passed_time":10.81230953,"remaining_time":4.546084687},
{"learn":[0.2987567616],"iteration":704,"passed_time":10.82813394,"remaining_time":4.530921295},
{"learn":[0.2986331144],"iteration":705,"passed_time":10.8420476,"remaining_time":4.514960333},
{"learn":[0.2984804388],"iteration":706,"passed_time":10.85743223,"remaining_time":4.49961477},
{"learn":[0.2983821806],"iteration":707,"passed_time":10.87129793,"remaining_time":4.483642647},
{"learn":[0.2982838464],"iteration":708,"passed_time":10.8866121,"remaining_time":4.468270975},
{"learn":[0.2981209574],"iteration":709,"passed_time":10.90252603,"remaining_time":4.453144434},
{"learn":[0.2979565696],"iteration":710,"passed_time":10.91722037,"remaining_time":4.437519953},
{"learn":[0.2978009392],"iteration":711,"passed_time":10.93270497,"remaining_time":4.422217741},
{"learn":[0.2977098076],"iteration":712,"passed_time":10.94795704,"remaining_time":4.406821418},
{"learn":[0.2975567068],"iteration":713,"passed_time":10.96290145,"remaining_time":4.391302261},
{"learn":[0.2973722947],"iteration":714,"passed_time":10.97800098,"remaining_time":4.375846546},
{"learn":[0.2972179323],"iteration":715,"passed_time":10.99321232,"remaining_time":4.360436173},
{"learn":[0.2970242646],"iteration":716,"passed_time":11.01044587,"remaining_time":4.345824522},
{"learn":[0.2968898991],"iteration":717,"passed_time":11.02660413,"remaining_time":4.330783238},
{"learn":[0.2967645165],"iteration":718,"passed_time":11.04296564,"remaining_time":4.315818281},
{"learn":[0.2965822951],"iteration":719,"passed_time":11.05942501,"remaining_time":4.300887503},
{"learn":[0.2963180667],"iteration":720,"passed_time":11.07646052,"remaining_time":4.286175428},
{"learn":[0.2961835973],"iteration":721,"passed_time":11.091245,"remaining_time":4.270590181},
{"learn":[0.296118293],"iteration":722,"passed_time":11.10537179,"remaining_time":4.254755165},
{"learn":[0.2959879132],"iteration":723,"passed_time":11.12090824,"remaining_time":4.239462258},
{"learn":[0.2957137975],"iteration":724,"passed_time":11.13778622,"remaining_time":4.224677532},
{"learn":[0.2954847571],"iteration":725,"passed_time":11.15334996,"remaining_time":4.20939103},
{"learn":[0.2953729097],"iteration":726,"passed_time":11.16789431,"remaining_time":4.193720974},
{"learn":[0.2950887187],"iteration":727,"passed_time":11.18216256,"remaining_time":4.177950848},
{"learn":[0.2949952684],"iteration":728,"passed_time":11.19714547,"remaining_time":4.162450509},
{"learn":[0.2949235732],"iteration":729,"passed_time":11.21181015,"remaining_time":4.14683389},
{"learn":[0.2946600424],"iteration":730,"passed_time":11.22870482,"remaining_time":4.132040487},
{"learn":[0.2944689254],"iteration":731,"passed_time":11.24353283,"remaining_time":4.116484698},
{"learn":[0.2942842939],"iteration":732,"passed_time":11.25861094,"remaining_time":4.101021994},
{"learn":[0.2941755116],"iteration":733,"passed_time":11.27334446,"remaining_time":4.085435458},
{"learn":[0.2940666745],"iteration":734,"passed_time":11.28758135,"remaining_time":4.069672189},
{"learn":[0.2938894544],"iteration":735,"passed_time":11.30329873,"remaining_time":4.05444411},
{"learn":[0.2936439816],"iteration":736,"passed_time":11.31948813,"remaining_time":4.039383145},
{"learn":[0.2935430707],"iteration":737,"passed_time":11.33627893,"remaining_time":4.02453263},
{"learn":[0.2934132881],"iteration":738,"passed_time":11.35118257,"remaining_time":4.009010353},
{"learn":[0.2932989956],"iteration":739,"passed_time":11.36543127,"remaining_time":3.993259636},
{"learn":[0.293117289],"iteration":740,"passed_time":11.38132689,"remaining_time":3.978088615},
{"learn":[0.2930332048],"iteration":741,"passed_time":11.39541034,"remaining_time":3.962285536},
{"learn":[0.292821723],"iteration":742,"passed_time":11.41171492,"remaining_time":3.947255361},
{"learn":[0.2926551429],"iteration":743,"passed_time":11.42670418,"remaining_time":3.93176918},
{"learn":[0.2924854226],"iteration":744,"passed_time":11.44248283,"remaining_time":3.916554527},
{"learn":[0.2921861851],"iteration":745,"passed_time":11.4604222,"remaining_time":3.902074047},
{"learn":[0.2920348361],"iteration":746,"passed_time":11.47589506,"remaining_time":3.88674893},
{"learn":[0.2918595428],"iteration":747,"passed_time":11.49191824,"remaining_time":3.871608819},
{"learn":[0.2916547995],"iteration":748,"passed_time":11.50865581,"remaining_time":3.856705753},
{"learn":[0.2914912955],"iteration":749,"passed_time":11.52374966,"remaining_time":3.841249887},
{"learn":[0.291408732],"iteration":750,"passed_time":11.53821814,"remaining_time":3.825587638},
{"learn":[0.2912054135],"iteration":751,"passed_time":11.5536858,"remaining_time":3.810258084},
{"learn":[0.291061797],"iteration":752,"passed_time":11.56930435,"remaining_time":3.794977655},
{"learn":[0.2908758105],"iteration":753,"passed_time":11.58447599,"remaining_time":3.779550523},
{"learn":[0.29075753],"iteration":754,"passed_time":11.5990939,"remaining_time":3.763944378},
{"learn":[0.2906176877],"iteration":755,"passed_time":11.61321405,"remaining_time":3.748180195},
{"learn":[0.2904673492],"iteration":756,"passed_time":11.62755945,"remaining_time":3.732492663},
{"learn":[0.2903976634],"iteration":757,"passed_time":11.64205994,"remaining_time":3.716858187},
{"learn":[0.2901493222],"iteration":758,"passed_time":11.65729265,"remaining_time":3.701459194},
{"learn":[0.2900514571],"iteration":759,"passed_time":11.67180898,"remaining_time":3.685834415},
{"learn":[0.2899501498],"iteration":760,"passed_time":11.68619671,"remaining_time":3.670172161},
{"learn":[0.2897998698],"iteration":761,"passed_time":11.70166866,"remaining_time":3.654851892},
{"learn":[0.2896966336],"iteration":762,"passed_time":11.71689172,"remaining_time":3.639453914},
{"learn":[0.2895146912],"iteration":763,"passed_time":11.73377192,"remaining_time":3.624568291},
{"learn":[0.289395287],"iteration":764,"passed_time":11.74895304,"remaining_time":3.609155509},
{"learn":[0.2892084583],"iteration":765,"passed_time":11.76310879,"remaining_time":3.593430101},
{"learn":[0.2890536536],"iteration":766,"passed_time":11.77935015,"remaining_time":3.578342353},
{"learn":[0.2887936196],"iteration":767,"passed_time":11.79535956,"remaining_time":3.563181534},
{"learn":[0.2886504535],"iteration":768,"passed_time":11.81049049,"remaining_time":3.547754622},
{"learn":[0.2885049242],"iteration":769,"passed_time":11.82552356,"remaining_time":3.532299244},
{"learn":[0.2882874621],"iteration":770,"passed_time":11.84220553,"remaining_time":3.517334716},
{"learn":[0.2882169908],"iteration":771,"passed_time":11.85783068,"remaining_time":3.502053621},
{"learn":[0.2881108365],"iteration":772,"passed_time":11.87230707,"remaining_time":3.486434289},
{"learn":[0.2879144329],"iteration":773,"passed_time":11.88878892,"remaining_time":3.471403483},
{"learn":[0.2877376392],"iteration":774,"passed_time":11.90378252,"remaining_time":3.455936862},
{"learn":[0.2875174839],"iteration":775,"passed_time":11.9187979,"remaining_time":3.440477744},
{"learn":[0.2873454629],"iteration":776,"passed_time":11.93305908,"remaining_time":3.424803315},
{"learn":[0.2872751745],"iteration":777,"passed_time":11.94780513,"remaining_time":3.409270873},
{"learn":[0.2871350274],"iteration":778,"passed_time":11.9637673,"remaining_time":3.394085461},
{"learn":[0.2869326969],"iteration":779,"passed_time":11.97941636,"remaining_time":3.378809741},
{"learn":[0.286746617],"iteration":780,"passed_time":11.99425749,"remaining_time":3.363306517},
{"learn":[0.2865480457],"iteration":781,"passed_time":12.00913381,"remaining_time":3.347814798},
{"learn":[0.2864002602],"iteration":782,"passed_time":12.02497977,"remaining_time":3.332593371},
{"learn":[0.2862995605],"iteration":783,"passed_time":12.03938337,"remaining_time":3.316972971},
{"learn":[0.2861446046],"iteration":784,"passed_time":12.0531357,"remaining_time":3.301177294},
{"learn":[0.2860420523],"iteration":785,"passed_time":12.06883606,"remaining_time":3.285917198},
{"learn":[0.2859472533],"iteration":786,"passed_time":12.08329534,"remaining_time":3.270320085},
{"learn":[0.2856613681],"iteration":787,"passed_time":12.09960628,"remaining_time":3.255224025},
{"learn":[0.2855044494],"iteration":788,"passed_time":12.11365168,"remaining_time":3.239519016},
{"learn":[0.2853595683],"iteration":789,"passed_time":12.12882934,"remaining_time":3.224119192},
{"learn":[0.2852185403],"iteration":790,"passed_time":12.14343173,"remaining_time":3.208567927},
{"learn":[0.2851433885],"iteration":791,"passed_time":12.15861581,"remaining_time":3.193171828},
{"learn":[0.2848125411],"iteration":792,"passed_time":12.17418817,"remaining_time":3.177877617},
{"learn":[0.2846642956],"iteration":793,"passed_time":12.18881527,"remaining_time":3.162337464},
{"learn":[0.2844636531],"iteration":794,"passed_time":12.20550841,"remaining_time":3.147332357},
{"learn":[0.2842248301],"iteration":795,"passed_time":12.22139595,"remaining_time":3.13211655},
{"learn":[0.2840106239],"iteration":796,"passed_time":12.23643972,"remaining_time":3.116684146},
{"learn":[0.2838208212],"iteration":797,"passed_time":12.25120421,"remaining_time":3.101182018},
{"learn":[0.2837262715],"iteration":798,"passed_time":12.26648538,"remaining_time":3.085811716},
{"learn":[0.2835836798],"iteration":799,"passed_time":12.28176068,"remaining_time":3.070440169},
{"learn":[0.2835195587],"iteration":800,"passed_time":12.29571126,"remaining_time":3.054739751},
{"learn":[0.2833921229],"iteration":801,"passed_time":12.3095002,"remaining_time":3.03900379},
{"learn":[0.2832959951],"iteration":802,"passed_time":12.32620171,"remaining_time":3.02398722},
{"learn":[0.2831760463],"iteration":803,"passed_time":12.34300285,"remaining_time":3.008990746},
{"learn":[0.2829346965],"iteration":804,"passed_time":12.3593732,"remaining_time":2.993885434},
{"learn":[0.282830988],"iteration":805,"passed_time":12.37459611,"remaining_time":2.978500802},
{"learn":[0.2826855975],"iteration":806,"passed_time":12.38991702,"remaining_time":2.963140005},
{"learn":[0.2824642748],"iteration":807,"passed_time":12.40503108,"remaining_time":2.947730157},
{"learn":[0.2823394158],"iteration":808,"passed_time":12.41926931,"remaining_time":2.932114262},
{"learn":[0.2821268348],"iteration":809,"passed_time":12.43553261,"remaining_time":2.916976786},
{"learn":[0.2819238007],"iteration":810,"passed_time":12.45150436,"remaining_time":2.901768587},
{"learn":[0.2816892733],"iteration":811,"passed_time":12.46770082,"remaining_time":2.886610535},
{"learn":[0.2814232878],"iteration":812,"passed_time":12.48291316,"remaining_time":2.871223569},
{"learn":[0.2812058444],"iteration":813,"passed_time":12.49997324,"remaining_time":2.856259242},
{"learn":[0.2809630545],"iteration":814,"passed_time":12.51659156,"remaining_time":2.841189494},
{"learn":[0.2808137865],"iteration":815,"passed_time":12.5335589,"remaining_time":2.826194655},
{"learn":[0.2807467436],"iteration":816,"passed_time":12.54839304,"remaining_time":2.810717169},
{"learn":[0.2806269466],"iteration":817,"passed_time":12.5638447,"remaining_time":2.795378651},
{"learn":[0.2804598779],"iteration":818,"passed_time":12.57899953,"remaining_time":2.779974255},
{"learn":[0.2802824525],"iteration":819,"passed_time":12.59397936,"remaining_time":2.764532054},
{"learn":[0.2801453396],"iteration":820,"passed_time":12.60917003,"remaining_time":2.74913695},
{"learn":[0.2798896529],"iteration":821,"passed_time":12.62550166,"remaining_time":2.733989412},
{"learn":[0.2797909338],"iteration":822,"passed_time":12.64017978,"remaining_time":2.71848338},
{"learn":[0.2796175544],"iteration":823,"passed_time":12.65487596,"remaining_time":2.702983214},
{"learn":[0.2793680099],"iteration":824,"passed_time":12.67019968,"remaining_time":2.687618115},
{"learn":[0.2791584943],"iteration":825,"passed_time":12.68597126,"remaining_time":2.672347457},
{"learn":[0.2789958752],"iteration":826,"passed_time":12.70127993,"remaining_time":2.656978753},
{"learn":[0.2787881832],"iteration":827,"passed_time":12.71670264,"remaining_time":2.641633881},
{"learn":[0.2786592559],"iteration":828,"passed_time":12.73143258,"remaining_time":2.626145923},
{"learn":[0.2785989204],"iteration":829,"passed_time":12.74554642,"remaining_time":2.610533603},
{"learn":[0.2783108567],"iteration":830,"passed_time":12.76117006,"remaining_time":2.595231938},
{"learn":[0.2782598369],"iteration":831,"passed_time":12.77516196,"remaining_time":2.579600011},
{"learn":[0.2781119414],"iteration":832,"passed_time":12.78986314,"remaining_time":2.564114219},
{"learn":[0.2779355157],"iteration":833,"passed_time":12.8073075,"remaining_time":2.549176314},
{"learn":[0.2778068538],"iteration":834,"passed_time":12.82242782,"remaining_time":2.533773162},
{"learn":[0.2776741454],"iteration":835,"passed_time":12.8398559,"remaining_time":2.518823405},
{"learn":[0.2775176826],"iteration":836,"passed_time":12.85519927,"remaining_time":2.503461745},
{"learn":[0.2774516512],"iteration":837,"passed_time":12.87101879,"remaining_time":2.488192176},
{"learn":[0.2772246836],"iteration":838,"passed_time":12.88683868,"remaining_time":2.472921369},
{"learn":[0.2771576374],"iteration":839,"passed_time":12.90236111,"remaining_time":2.457592593},
{"learn":[0.277057578],"iteration":840,"passed_time":12.9172886,"remaining_time":2.442150877},
{"learn":[0.2768553333],"iteration":841,"passed_time":12.93336943,"remaining_time":2.426926806},
{"learn":[0.276616824],"iteration":842,"passed_time":12.94912985,"remaining_time":2.411641027},
{"learn":[0.2765632833],"iteration":843,"passed_time":12.96299801,"remaining_time":2.396004371},
{"learn":[0.2763987508],"iteration":844,"passed_time":12.97888984,"remaining_time":2.380743107},
{"learn":[0.2763358213],"iteration":845,"passed_time":12.99458742,"remaining_time":2.365444992},
{"learn":[0.2762017449],"iteration":846,"passed_time":13.01025199,"remaining_time":2.35013997},
{"learn":[0.2759675835],"iteration":847,"passed_time":13.02565752,"remaining_time":2.334787669},
{"learn":[0.275825938],"iteration":848,"passed_time":13.04058362,"remaining_time":2.319349973},
{"learn":[0.2756903818],"iteration":849,"passed_time":13.0573672,"remaining_time":2.30424127},
{"learn":[0.2756161833],"iteration":850,"passed_time":13.07202206,"remaining_time":2.288755919},
{"learn":[0.275364258],"iteration":851,"passed_time":13.08790145,"remaining_time":2.273485228},
{"learn":[0.2752317397],"iteration":852,"passed_time":13.10308453,"remaining_time":2.258093113},
{"learn":[0.2751103152],"iteration":853,"passed_time":13.11890285,"remaining_time":2.242810089},
{"learn":[0.2749503248],"iteration":854,"passed_time":13.13599852,"remaining_time":2.227742439},
{"learn":[0.2746646889],"iteration":855,"passed_time":13.15150421,"remaining_time":2.212402577},
{"learn":[0.27454128],"iteration":856,"passed_time":13.16656892,"remaining_time":2.196988747},
{"learn":[0.2744333328],"iteration":857,"passed_time":13.18327272,"remaining_time":2.181847001},
{"learn":[0.2742729635],"iteration":858,"passed_time":13.1998285,"remaining_time":2.166677321},
{"learn":[0.2741021924],"iteration":859,"passed_time":13.2157443,"remaining_time":2.151400235},
{"learn":[0.2739344659],"iteration":860,"passed_time":13.23117488,"remaining_time":2.136043331},
{"learn":[0.2737281666],"iteration":861,"passed_time":13.24726484,"remaining_time":2.12079182},
{"learn":[0.2735865273],"iteration":862,"passed_time":13.26288502,"remaining_time":2.105463787},
{"learn":[0.2733308874],"iteration":863,"passed_time":13.27853615,"remaining_time":2.09013995},
{"learn":[0.2732140777],"iteration":864,"passed_time":13.29478864,"remaining_time":2.074909209},
{"learn":[0.2730259738],"iteration":865,"passed_time":13.31060257,"remaining_time":2.05960825},
{"learn":[0.2728285075],"iteration":866,"passed_time":13.32605256,"remaining_time":2.044250277},
{"learn":[0.2726867122],"iteration":867,"passed_time":13.34052896,"remaining_time":2.028744036},
{"learn":[0.2726200276],"iteration":868,"passed_time":13.35566767,"remaining_time":2.013340006},
{"learn":[0.2724470983],"iteration":869,"passed_time":13.37044287,"remaining_time":1.997882268},
{"learn":[0.2723096897],"iteration":870,"passed_time":13.38595722,"remaining_time":1.982535569},
{"learn":[0.2721618354],"iteration":871,"passed_time":13.40176177,"remaining_time":1.967231086},
{"learn":[0.2720762203],"iteration":872,"passed_time":13.41623214,"remaining_time":1.951731366},
{"learn":[0.2719881926],"iteration":873,"passed_time":13.43089152,"remaining_time":1.936261249},
{"learn":[0.2717547391],"iteration":874,"passed_time":13.44638089,"remaining_time":1.920911556},
{"learn":[0.2716553205],"iteration":875,"passed_time":13.46124159,"remaining_time":1.905472555},
{"learn":[0.2714865147],"iteration":876,"passed_time":13.47748402,"remaining_time":1.89022866},
{"learn":[0.2713174123],"iteration":877,"passed_time":13.49321787,"remaining_time":1.874911822},
{"learn":[0.2712455832],"iteration":878,"passed_time":13.50848469,"remaining_time":1.859529747},
{"learn":[0.2710372336],"iteration":879,"passed_time":13.52404391,"remaining_time":1.844187806},
{"learn":[0.270790043],"iteration":880,"passed_time":13.54007346,"remaining_time":1.828908902},
{"learn":[0.2706920424],"iteration":881,"passed_time":13.55530424,"remaining_time":1.813521428},
{"learn":[0.2704420737],"iteration":882,"passed_time":13.57066357,"remaining_time":1.798151346},
{"learn":[0.2702944596],"iteration":883,"passed_time":13.58567466,"remaining_time":1.782735589},
{"learn":[0.2701285477],"iteration":884,"passed_time":13.60123556,"remaining_time":1.767392191},
{"learn":[0.2699349861],"iteration":885,"passed_time":13.61647569,"remaining_time":1.75200703},
{"learn":[0.2698108778],"iteration":886,"passed_time":13.63283331,"remaining_time":1.736764559},
{"learn":[0.2697225465],"iteration":887,"passed_time":13.64808533,"remaining_time":1.721380131},
{"learn":[0.26963569],"iteration":888,"passed_time":13.66212376,"remaining_time":1.705844475},
{"learn":[0.2695105302],"iteration":889,"passed_time":13.67809039,"remaining_time":1.690550498},
{"learn":[0.2693229063],"iteration":890,"passed_time":13.69518565,"remaining_time":1.675393082},
{"learn":[0.2692017738],"iteration":891,"passed_time":13.71107956,"remaining_time":1.660085866},
{"learn":[0.2690410087],"iteration":892,"passed_time":13.7254034,"remaining_time":1.64458921},
{"learn":[0.2689338434],"iteration":893,"passed_time":13.7403514,"remaining_time":1.629169182},
{"learn":[0.2688620311],"iteration":894,"passed_time":13.75551602,"remaining_time":1.613775622},
{"learn":[0.268567134],"iteration":895,"passed_time":13.77137549,"remaining_time":1.598463226},
{"learn":[0.2683584289],"iteration":896,"passed_time":13.78656554,"remaining_time":1.583072744},
{"learn":[0.2682853046],"iteration":897,"passed_time":13.79983996,"remaining_time":1.567465118},
{"learn":[0.2681765533],"iteration":898,"passed_time":13.81463823,"remaining_time":1.552033883},
{"learn":[0.2680555157],"iteration":899,"passed_time":13.83013998,"remaining_time":1.53668222},
{"learn":[0.2679468938],"iteration":900,"passed_time":13.84460295,"remaining_time":1.521216084},
{"learn":[0.2677781638],"iteration":901,"passed_time":13.8602379,"remaining_time":1.505879506},
{"learn":[0.2675497501],"iteration":902,"passed_time":13.87531277,"remaining_time":1.490482102},
{"learn":[0.2674506576],"iteration":903,"passed_time":13.89018153,"remaining_time":1.475063525},
{"learn":[0.2673814034],"iteration":904,"passed_time":13.90567317,"remaining_time":1.459711548},
{"learn":[0.2673009671],"iteration":905,"passed_time":13.92058309,"remaining_time":1.444298908},
{"learn":[0.2671767198],"iteration":906,"passed_time":13.93608616,"remaining_time":1.428948195},
{"learn":[0.2670788646],"iteration":907,"passed_time":13.9497715,"remaining_time":1.413412972},
{"learn":[0.2669767365],"iteration":908,"passed_time":13.96589944,"remaining_time":1.398126347},
{"learn":[0.2668845784],"iteration":909,"passed_time":13.9802269,"remaining_time":1.382659803},
{"learn":[0.2667350937],"iteration":910,"passed_time":13.99533378,"remaining_time":1.367271906},
{"learn":[0.2665523746],"iteration":911,"passed_time":14.01092097,"remaining_time":1.351930971},
{"learn":[0.2664067253],"iteration":912,"passed_time":14.0257602,"remaining_time":1.336518223},
{"learn":[0.2661600963],"iteration":913,"passed_time":14.04074834,"remaining_time":1.321120741},
{"learn":[0.2660227388],"iteration":914,"passed_time":14.05469828,"remaining_time":1.305627709},
{"learn":[0.2658605125],"iteration":915,"passed_time":14.07003912,"remaining_time":1.290265596},
{"learn":[0.2656950201],"iteration":916,"passed_time":14.08595148,"remaining_time":1.274955259},
{"learn":[0.2656193848],"iteration":917,"passed_time":14.1014147,"remaining_time":1.259603492},
{"learn":[0.2655192983],"iteration":918,"passed_time":14.11833522,"remaining_time":1.244379927},
{"learn":[0.2654305272],"iteration":919,"passed_time":14.13358267,"remaining_time":1.229007189},
{"learn":[0.2652655048],"iteration":920,"passed_time":14.14860435,"remaining_time":1.213615357},
{"learn":[0.2651422715],"iteration":921,"passed_time":14.1629207,"remaining_time":1.198164658},
{"learn":[0.2650309425],"iteration":922,"passed_time":14.17731744,"remaining_time":1.182723123},
{"learn":[0.2649386958],"iteration":923,"passed_time":14.19275023,"remaining_time":1.167369067},
{"learn":[0.2647802214],"iteration":924,"passed_time":14.20700951,"remaining_time":1.15191969},
{"learn":[0.2646576346],"iteration":925,"passed_time":14.22332521,"remaining_time":1.13663722},
{"learn":[0.2645210794],"iteration":926,"passed_time":14.23878456,"remaining_time":1.121285084},
{"learn":[0.2644061998],"iteration":927,"passed_time":14.25429863,"remaining_time":1.105936963},
{"learn":[0.2642615372],"iteration":928,"passed_time":14.26989603,"remaining_time":1.090594853},
{"learn":[0.2641803023],"iteration":929,"passed_time":14.28409018,"remaining_time":1.075146573},
{"learn":[0.2640865308],"iteration":930,"passed_time":14.29860393,"remaining_time":1.059724674},
{"learn":[0.2639419951],"iteration":931,"passed_time":14.31419067,"remaining_time":1.04438301},
{"learn":[0.2638058568],"iteration":932,"passed_time":14.3295851,"remaining_time":1.029027011},
{"learn":[0.2636671947],"iteration":933,"passed_time":14.34490811,"remaining_time":1.013665884},
{"learn":[0.263471348],"iteration":934,"passed_time":14.36015926,"remaining_time":0.9982998414},
{"learn":[0.2633842385],"iteration":935,"passed_time":14.37592374,"remaining_time":0.9829691447},
{"learn":[0.2631600773],"iteration":936,"passed_time":14.39232208,"remaining_time":0.9676801396},
{"learn":[0.2630569733],"iteration":937,"passed_time":14.40753038,"remaining_time":0.9523101104},
{"learn":[0.262938684],"iteration":938,"passed_time":14.42177091,"remaining_time":0.9368775562},
{"learn":[0.2628248429],"iteration":939,"passed_time":14.43781954,"remaining_time":0.9215629494},
{"learn":[0.2627715514],"iteration":940,"passed_time":14.45186944,"remaining_time":0.9061214634},
{"learn":[0.2626398651],"iteration":941,"passed_time":14.46720783,"remaining_time":0.8907622654},
{"learn":[0.2625464668],"iteration":942,"passed_time":14.48405394,"remaining_time":0.8754942469},
{"learn":[0.2623590412],"iteration":943,"passed_time":14.50004211,"remaining_time":0.8601719899},
{"learn":[0.2622025496],"iteration":944,"passed_time":14.51562079,"remaining_time":0.8448244905},
{"learn":[0.2620570464],"iteration":945,"passed_time":14.53043234,"remaining_time":0.8294327129},
{"learn":[0.2619445512],"iteration":946,"passed_time":14.54610776,"remaining_time":0.8140905085},
{"learn":[0.2618763573],"iteration":947,"passed_time":14.56060947,"remaining_time":0.7986832199},
{"learn":[0.2617340731],"iteration":948,"passed_time":14.5760327,"remaining_time":0.7833273634},
{"learn":[0.2616662421],"iteration":949,"passed_time":14.59101205,"remaining_time":0.7679480027},
{"learn":[0.2614608934],"iteration":950,"passed_time":14.60758808,"remaining_time":0.752651752},
{"learn":[0.2612967236],"iteration":951,"passed_time":14.62375655,"remaining_time":0.7373322631},
{"learn":[0.2610365717],"iteration":952,"passed_time":14.64046629,"remaining_time":0.7220376871},
{"learn":[0.2608992392],"iteration":953,"passed_time":14.65751192,"remaining_time":0.7067563399},
{"learn":[0.2607887858],"iteration":954,"passed_time":14.67165244,"remaining_time":0.6913344083},
{"learn":[0.2607092912],"iteration":955,"passed_time":14.68646563,"remaining_time":0.675946117},
{"learn":[0.2605470096],"iteration":956,"passed_time":14.7037172,"remaining_time":0.660668589},
{"learn":[0.2603579529],"iteration":957,"passed_time":14.71931338,"remaining_time":0.6453143654},
{"learn":[0.2601518402],"iteration":958,"passed_time":14.73499051,"remaining_time":0.629963098},
{"learn":[0.2600556013],"iteration":959,"passed_time":14.7505699,"remaining_time":0.6146070791},
{"learn":[0.2597869048],"iteration":960,"passed_time":14.76656728,"remaining_time":0.5992675586},
{"learn":[0.2596476804],"iteration":961,"passed_time":14.78319206,"remaining_time":0.5839514535},
{"learn":[0.2594967512],"iteration":962,"passed_time":14.79759207,"remaining_time":0.568547151},
{"learn":[0.2593836126],"iteration":963,"passed_time":14.81288249,"remaining_time":0.5531781842},
{"learn":[0.2592966145],"iteration":964,"passed_time":14.82722021,"remaining_time":0.5377748264},
{"learn":[0.2592383975],"iteration":965,"passed_time":14.84210011,"remaining_time":0.5223927576},
{"learn":[0.2591201169],"iteration":966,"passed_time":14.85871216,"remaining_time":0.5070708389},
{"learn":[0.2589498831],"iteration":967,"passed_time":14.87394018,"remaining_time":0.4917005018},
{"learn":[0.2587652717],"iteration":968,"passed_time":14.89034296,"remaining_time":0.4763680411},
{"learn":[0.2587028719],"iteration":969,"passed_time":14.90523043,"remaining_time":0.4609865081},
{"learn":[0.2585150922],"iteration":970,"passed_time":14.92039378,"remaining_time":0.4456142325},
{"learn":[0.2584455272],"iteration":971,"passed_time":14.93613576,"remaining_time":0.4302590549},
{"learn":[0.2583402204],"iteration":972,"passed_time":14.95270144,"remaining_time":0.4149259391},
{"learn":[0.258115808],"iteration":973,"passed_time":14.96803601,"remaining_time":0.3995574295},
{"learn":[0.2578747036],"iteration":974,"passed_time":14.98416002,"remaining_time":0.3842092312},
{"learn":[0.2577045518],"iteration":975,"passed_time":14.99924063,"remaining_time":0.3688337859},
{"learn":[0.2575616928],"iteration":976,"passed_time":15.01517124,"remaining_time":0.3534789546},
{"learn":[0.2573290119],"iteration":977,"passed_time":15.03125886,"remaining_time":0.3381264775},
{"learn":[0.2571450527],"iteration":978,"passed_time":15.04600541,"remaining_time":0.322743732},
{"learn":[0.257079835],"iteration":979,"passed_time":15.0595828,"remaining_time":0.3073384245},
{"learn":[0.2568772407],"iteration":980,"passed_time":15.07557507,"remaining_time":0.291983615},
{"learn":[0.2567274341],"iteration":981,"passed_time":15.09100556,"remaining_time":0.2766172099},
{"learn":[0.2565763567],"iteration":982,"passed_time":15.10734028,"remaining_time":0.2612663121},
{"learn":[0.2564972685],"iteration":983,"passed_time":15.12256164,"remaining_time":0.2458953112},
{"learn":[0.2562879903],"iteration":984,"passed_time":15.14002521,"remaining_time":0.2305587596},
{"learn":[0.2562318265],"iteration":985,"passed_time":15.15358547,"remaining_time":0.2151624712},
{"learn":[0.2560985092],"iteration":986,"passed_time":15.16891413,"remaining_time":0.1997931953},
{"learn":[0.2558486942],"iteration":987,"passed_time":15.18453915,"remaining_time":0.1844276011},
{"learn":[0.2557626675],"iteration":988,"passed_time":15.19932969,"remaining_time":0.1690522008},
{"learn":[0.2556809454],"iteration":989,"passed_time":15.21383441,"remaining_time":0.153675095},
{"learn":[0.2555849558],"iteration":990,"passed_time":15.22877244,"remaining_time":0.1383036851},
{"learn":[0.2555217585],"iteration":991,"passed_time":15.2445679,"remaining_time":0.1229400637},
{"learn":[0.2553589336],"iteration":992,"passed_time":15.26123015,"remaining_time":0.1075816828},
{"learn":[0.2551677339],"iteration":993,"passed_time":15.27654291,"remaining_time":0.09221253264},
{"learn":[0.2550192864],"iteration":994,"passed_time":15.2924733,"remaining_time":0.07684659949},
{"learn":[0.2549098597],"iteration":995,"passed_time":15.30764568,"remaining_time":0.06147648866},
{"learn":[0.254748867],"iteration":996,"passed_time":15.32348262,"remaining_time":0.04610877419},
{"learn":[0.2545847994],"iteration":997,"passed_time":15.33937137,"remaining_time":0.03074022319},
{"learn":[0.2544659028],"iteration":998,"passed_time":15.35322288,"remaining_time":0.01536859147},
{"learn":[0.2542311965],"iteration":999,"passed_time":15.3690974,"remaining_time":0}
]}